[
  {
    "symbol": "LINK",
    "tier": "Directional",
    "probability": 0.04045454545454546,
    "threshold": 0.8,
    "accuracy": 1.0,
    "passed": 0.0,
    "last_seen": "2026-04-02 15:59:23,586",
    "count": 22
  },
  {
    "symbol": "TRAC",
    "tier": "Generalist",
    "probability": 0.331,
    "threshold": 0.75,
    "accuracy": 1.0,
    "passed": 0.0,
    "last_seen": "2026-04-02 15:58:15,128",
    "count": 20
  },
  {
    "symbol": "TRAC",
    "tier": "Crash",
    "probability": 0.0045,
    "threshold": 0.35,
    "accuracy": 1.0,
    "passed": 1.0,
    "last_seen": "2026-04-02 15:58:08,148",
    "count": 20
  },
  {
    "symbol": "TRAC",
    "tier": "Imbalance",
    "probability": 0.9275236263863249,
    "threshold": 0.8,
    "accuracy": 1.0,
    "passed": 0.9090909090909091,
    "last_seen": "2026-04-02 15:58:06,028",
    "count": 22
  },
  {
    "symbol": "AWE",
    "tier": "Directional",
    "probability": 0.7935714285714287,
    "threshold": 0.8,
    "accuracy": 1.0,
    "passed": 0.8571428571428571,
    "last_seen": "2026-04-02 15:58:05,943",
    "count": 14
  },
  {
    "symbol": "LTC",
    "tier": "Directional",
    "probability": 0.0004761904761904762,
    "threshold": 0.8,
    "accuracy": 1.0,
    "passed": 0.0,
    "last_seen": "2026-04-02 15:58:05,405",
    "count": 21
  },
  {
    "symbol": "TRAC",
    "tier": "Directional",
    "probability": 0.9945454545454545,
    "threshold": 0.8,
    "accuracy": 1.0,
    "passed": 1.0,
    "last_seen": "2026-04-02 15:58:05,355",
    "count": 22
  },
  {
    "symbol": "RLC",
    "tier": "Directional",
    "probability": 0.0007142857142857143,
    "threshold": 0.8,
    "accuracy": 1.0,
    "passed": 0.0,
    "last_seen": "2026-04-02 15:58:05,179",
    "count": 14
  },
  {
    "symbol": "MNDE",
    "tier": "Directional",
    "probability": 0.23347826086956522,
    "threshold": 0.8,
    "accuracy": 1.0,
    "passed": 0.0,
    "last_seen": "2026-04-02 15:58:05,126",
    "count": 23
  },
  {
    "symbol": "WAXL",
    "tier": "Directional",
    "probability": 0.21923076923076923,
    "threshold": 0.8,
    "accuracy": 1.0,
    "passed": 0.0,
    "last_seen": "2026-04-02 15:58:04,756",
    "count": 26
  },
  {
    "symbol": "SHPING",
    "tier": "Directional",
    "probability": 0.07625,
    "threshold": 0.8000000000000002,
    "accuracy": 1.0,
    "passed": 0.0,
    "last_seen": "2026-04-02 15:58:04,373",
    "count": 24
  },
  {
    "symbol": "WCFG",
    "tier": "Directional",
    "probability": 0.11000000000000001,
    "threshold": 0.8,
    "accuracy": 1.0,
    "passed": 0.0,
    "last_seen": "2026-04-02 15:57:59,750",
    "count": 20
  },
  {
    "symbol": "FX",
    "tier": "Directional",
    "probability": 0.0,
    "threshold": 0.8,
    "accuracy": 1.0,
    "passed": 0.0,
    "last_seen": "2026-04-02 15:57:46,198",
    "count": 19
  },
  {
    "symbol": "DASH",
    "tier": "Directional",
    "probability": 0.0,
    "threshold": 0.7840509786071918,
    "accuracy": 0.9800637232589896,
    "passed": 0.0,
    "last_seen": "2026-04-02 15:56:50,707",
    "count": 23
  },
  {
    "symbol": "ONDO",
    "tier": "Directional",
    "probability": 0.04476190476190477,
    "threshold": 0.8,
    "accuracy": 1.0,
    "passed": 0.0,
    "last_seen": "2026-04-02 15:56:50,520",
    "count": 21
  },
  {
    "symbol": "MANA",
    "tier": "Directional",
    "probability": 0.02,
    "threshold": 0.8,
    "accuracy": 1.0,
    "passed": 0.0,
    "last_seen": "2026-04-02 15:56:50,463",
    "count": 18
  },
  {
    "symbol": "T",
    "tier": "Directional",
    "probability": 0.03125,
    "threshold": 0.8,
    "accuracy": 1.0,
    "passed": 0.0,
    "last_seen": "2026-04-02 15:56:49,844",
    "count": 16
  },
  {
    "symbol": "SWFTC",
    "tier": "Generalist",
    "probability": 0.4904,
    "threshold": 0.75,
    "accuracy": 1.0,
    "passed": 0.0,
    "last_seen": "2026-04-02 15:56:13,920",
    "count": 25
  },
  {
    "symbol": "DIMO",
    "tier": "Generalist",
    "probability": 0.5109523809523809,
    "threshold": 0.5201109570041609,
    "accuracy": 0.6934812760055479,
    "passed": 0.09523809523809523,
    "last_seen": "2026-04-02 15:56:11,930",
    "count": 21
  },
  {
    "symbol": "SWFTC",
    "tier": "Crash",
    "probability": 0.15439999999999998,
    "threshold": 0.35,
    "accuracy": 1.0,
    "passed": 1.0,
    "last_seen": "2026-04-02 15:56:10,891",
    "count": 25
  },
  {
    "symbol": "SUKU",
    "tier": "Crash",
    "probability": 0.34950000000000003,
    "threshold": 0.35,
    "accuracy": 0.1,
    "passed": 0.1,
    "last_seen": "2026-04-02 15:56:10,679",
    "count": 20
  },
  {
    "symbol": "SUKU",
    "tier": "Imbalance",
    "probability": 1.0,
    "threshold": 0.8,
    "accuracy": 1.0,
    "passed": 1.0,
    "last_seen": "2026-04-02 15:56:09,612",
    "count": 20
  },
  {
    "symbol": "SWFTC",
    "tier": "Imbalance",
    "probability": 0.9615384615384616,
    "threshold": 0.8,
    "accuracy": 1.0,
    "passed": 0.9615384615384616,
    "last_seen": "2026-04-02 15:55:59,503",
    "count": 26
  },
  {
    "symbol": "DIMO",
    "tier": "Crash",
    "probability": 0.01,
    "threshold": 0.35,
    "accuracy": 1.0,
    "passed": 1.0,
    "last_seen": "2026-04-02 15:55:57,672",
    "count": 21
  },
  {
    "symbol": "AVT",
    "tier": "Directional",
    "probability": 0.16952380952380952,
    "threshold": 0.7136636636636637,
    "accuracy": 0.8920795795795795,
    "passed": 0.0,
    "last_seen": "2026-04-02 15:55:56,641",
    "count": 21
  },
  {
    "symbol": "FLR",
    "tier": "Directional",
    "probability": 0.029999999999999995,
    "threshold": 0.7799864773495604,
    "accuracy": 0.9749830966869506,
    "passed": 0.0,
    "last_seen": "2026-04-02 15:55:56,318",
    "count": 11
  },
  {
    "symbol": "AERGO",
    "tier": "Directional",
    "probability": 0.08869565217391305,
    "threshold": 0.7715204613507818,
    "accuracy": 0.9644005766884772,
    "passed": 0.0,
    "last_seen": "2026-04-02 15:55:56,042",
    "count": 23
  },
  {
    "symbol": "POL",
    "tier": "Directional",
    "probability": 0.05,
    "threshold": 0.8,
    "accuracy": 1.0,
    "passed": 0.0,
    "last_seen": "2026-04-02 15:55:56,014",
    "count": 9
  },
  {
    "symbol": "ETC",
    "tier": "Directional",
    "probability": 0.0,
    "threshold": 0.7906905761159863,
    "accuracy": 0.9883632201449828,
    "passed": 0.0,
    "last_seen": "2026-04-02 15:55:55,976",
    "count": 14
  },
  {
    "symbol": "BARD",
    "tier": "Directional",
    "probability": 0.8768181818181818,
    "threshold": 0.8,
    "accuracy": 1.0,
    "passed": 0.9545454545454546,
    "last_seen": "2026-04-02 15:55:55,793",
    "count": 22
  },
  {
    "symbol": "SWFTC",
    "tier": "Directional",
    "probability": 0.9719230769230769,
    "threshold": 0.8,
    "accuracy": 1.0,
    "passed": 1.0,
    "last_seen": "2026-04-02 15:55:55,774",
    "count": 26
  },
  {
    "symbol": "VELO",
    "tier": "Directional",
    "probability": 0.011666666666666665,
    "threshold": 0.8,
    "accuracy": 1.0,
    "passed": 0.0,
    "last_seen": "2026-04-02 15:55:55,758",
    "count": 18
  },
  {
    "symbol": "BIGTIME",
    "tier": "Directional",
    "probability": 0.020666666666666667,
    "threshold": 0.7714573877962683,
    "accuracy": 0.9643217347453352,
    "passed": 0.0,
    "last_seen": "2026-04-02 15:55:55,657",
    "count": 15
  },
  {
    "symbol": "DIMO",
    "tier": "Imbalance",
    "probability": 0.972122474289251,
    "threshold": 0.8,
    "accuracy": 1.0,
    "passed": 0.9545454545454546,
    "last_seen": "2026-04-02 15:55:55,345",
    "count": 22
  },
  {
    "symbol": "BCH",
    "tier": "Directional",
    "probability": 0.012727272727272728,
    "threshold": 0.7925425719318848,
    "accuracy": 0.9906782149148561,
    "passed": 0.0,
    "last_seen": "2026-04-02 15:55:55,073",
    "count": 22
  },
  {
    "symbol": "SUKU",
    "tier": "Directional",
    "probability": 0.9800000000000001,
    "threshold": 0.8,
    "accuracy": 1.0,
    "passed": 1.0,
    "last_seen": "2026-04-02 15:55:55,057",
    "count": 20
  },
  {
    "symbol": "DIMO",
    "tier": "Directional",
    "probability": 0.979090909090909,
    "threshold": 0.7694099134539734,
    "accuracy": 0.9617623918174666,
    "passed": 1.0,
    "last_seen": "2026-04-02 15:55:54,680",
    "count": 22
  },
  {
    "symbol": "AERO",
    "tier": "Directional",
    "probability": 0.03318181818181818,
    "threshold": 0.7822805578342904,
    "accuracy": 0.9778506972928631,
    "passed": 0.0,
    "last_seen": "2026-04-02 15:55:54,657",
    "count": 22
  },
  {
    "symbol": "INX",
    "tier": "Directional",
    "probability": 0.7210344827586207,
    "threshold": 0.8,
    "accuracy": 1.0,
    "passed": 0.0,
    "last_seen": "2026-04-02 15:55:54,519",
    "count": 29
  },
  {
    "symbol": "CELR",
    "tier": "Directional",
    "probability": 0.6329166666666667,
    "threshold": 0.8000000000000002,
    "accuracy": 1.0,
    "passed": 0.0,
    "last_seen": "2026-04-02 15:55:54,135",
    "count": 24
  },
  {
    "symbol": "SHDW",
    "tier": "Generalist",
    "probability": 0.435,
    "threshold": 0.75,
    "accuracy": 1.0,
    "passed": 0.0,
    "last_seen": "2026-04-02 15:55:17,630",
    "count": 18
  },
  {
    "symbol": "SHDW",
    "tier": "Crash",
    "probability": 0.021666666666666667,
    "threshold": 0.35,
    "accuracy": 1.0,
    "passed": 1.0,
    "last_seen": "2026-04-02 15:55:14,901",
    "count": 18
  },
  {
    "symbol": "SHDW",
    "tier": "Imbalance",
    "probability": 0.9999989949580805,
    "threshold": 0.8,
    "accuracy": 1.0,
    "passed": 1.0,
    "last_seen": "2026-04-02 15:55:13,846",
    "count": 18
  },
  {
    "symbol": "SHDW",
    "tier": "Directional",
    "probability": 0.99,
    "threshold": 0.8,
    "accuracy": 1.0,
    "passed": 1.0,
    "last_seen": "2026-04-02 15:55:10,686",
    "count": 18
  },
  {
    "symbol": "SPA",
    "tier": "Imbalance",
    "probability": 0.10225683826167535,
    "threshold": 0.8,
    "accuracy": 1.0,
    "passed": 0.05,
    "last_seen": "2026-04-02 15:54:30,743",
    "count": 20
  },
  {
    "symbol": "COSMOSDYDX",
    "tier": "Directional",
    "probability": 0.5595238095238096,
    "threshold": 0.8,
    "accuracy": 1.0,
    "passed": 0.0,
    "last_seen": "2026-04-02 15:54:30,727",
    "count": 21
  },
  {
    "symbol": "C2Z",
    "tier": "Directional",
    "probability": 0.9558333333333332,
    "threshold": 0.8000000000000002,
    "accuracy": 1.0,
    "passed": 0.9583333333333334,
    "last_seen": "2026-04-02 15:54:30,691",
    "count": 24
  },
  {
    "symbol": "EDGE",
    "tier": "Directional",
    "probability": 0.7795454545454544,
    "threshold": 0.7219807983830218,
    "accuracy": 0.9024759979787773,
    "passed": 1.0,
    "last_seen": "2026-04-02 15:54:30,614",
    "count": 22
  },
  {
    "symbol": "FLOCK",
    "tier": "Directional",
    "probability": 0.8904545454545455,
    "threshold": 0.8,
    "accuracy": 1.0,
    "passed": 0.9545454545454546,
    "last_seen": "2026-04-02 15:54:30,590",
    "count": 22
  },
  {
    "symbol": "CLANKER",
    "tier": "Directional",
    "probability": 1.0,
    "threshold": 0.8,
    "accuracy": 1.0,
    "passed": 1.0,
    "last_seen": "2026-04-02 15:54:30,450",
    "count": 19
  },
  {
    "symbol": "BOBA",
    "tier": "Directional",
    "probability": 0.13,
    "threshold": 0.7751236749116609,
    "accuracy": 0.968904593639576,
    "passed": 0.0,
    "last_seen": "2026-04-02 15:54:30,411",
    "count": 26
  },
  {
    "symbol": "BNB",
    "tier": "Directional",
    "probability": 0.08423076923076923,
    "threshold": 0.8,
    "accuracy": 1.0,
    "passed": 0.0,
    "last_seen": "2026-04-02 15:54:30,410",
    "count": 26
  },
  {
    "symbol": "EOS",
    "tier": "Directional",
    "probability": 0.04703703703703704,
    "threshold": 0.7856509812196667,
    "accuracy": 0.9820637265245833,
    "passed": 0.0,
    "last_seen": "2026-04-02 15:54:30,333",
    "count": 27
  },
  {
    "symbol": "AXS",
    "tier": "Directional",
    "probability": 0.18000000000000002,
    "threshold": 0.781097353175054,
    "accuracy": 0.9763716914688174,
    "passed": 0.0,
    "last_seen": "2026-04-02 15:54:30,329",
    "count": 21
  },
  {
    "symbol": "SPA",
    "tier": "Directional",
    "probability": 0.9994999999999999,
    "threshold": 0.8,
    "accuracy": 1.0,
    "passed": 1.0,
    "last_seen": "2026-04-02 15:54:30,212",
    "count": 20
  },
  {
    "symbol": "VET",
    "tier": "Directional",
    "probability": 0.025294117647058825,
    "threshold": 0.8,
    "accuracy": 1.0,
    "passed": 0.0,
    "last_seen": "2026-04-02 15:54:30,041",
    "count": 17
  },
  {
    "symbol": "XCN",
    "tier": "Directional",
    "probability": 0.1123076923076923,
    "threshold": 0.8,
    "accuracy": 1.0,
    "passed": 0.0,
    "last_seen": "2026-04-02 15:54:29,897",
    "count": 26
  },
  {
    "symbol": "CLV",
    "tier": "Generalist",
    "probability": 0.7808333333333334,
    "threshold": 0.6391820580474934,
    "accuracy": 0.8522427440633246,
    "passed": 1.0,
    "last_seen": "2026-04-02 15:53:04,274",
    "count": 24
  },
  {
    "symbol": "CLV",
    "tier": "Crash",
    "probability": 0.005,
    "threshold": 0.3499999999999999,
    "accuracy": 1.0,
    "passed": 1.0,
    "last_seen": "2026-04-02 15:53:03,586",
    "count": 24
  },
  {
    "symbol": "CLV",
    "tier": "Imbalance",
    "probability": 0.944807277259907,
    "threshold": 0.8000000000000002,
    "accuracy": 1.0,
    "passed": 1.0,
    "last_seen": "2026-04-02 15:53:02,927",
    "count": 24
  },
  {
    "symbol": "IOTX",
    "tier": "Generalist",
    "probability": 0.4945454545454545,
    "threshold": 0.75,
    "accuracy": 1.0,
    "passed": 0.0,
    "last_seen": "2026-04-02 15:53:00,620",
    "count": 22
  },
  {
    "symbol": "IOTX",
    "tier": "Crash",
    "probability": 0.01681818181818182,
    "threshold": 0.35,
    "accuracy": 1.0,
    "passed": 1.0,
    "last_seen": "2026-04-02 15:52:33,648",
    "count": 22
  },
  {
    "symbol": "NMR",
    "tier": "Imbalance",
    "probability": 0.0,
    "threshold": 0.8000000000000002,
    "accuracy": 1.0,
    "passed": 0.0,
    "last_seen": "2026-04-02 15:52:25,933",
    "count": 24
  },
  {
    "symbol": "STG",
    "tier": "Directional",
    "probability": 0.03966666666666666,
    "threshold": 0.8,
    "accuracy": 1.0,
    "passed": 0.0,
    "last_seen": "2026-04-02 15:52:25,893",
    "count": 30
  },
  {
    "symbol": "IOTX",
    "tier": "Imbalance",
    "probability": 0.9459594784202867,
    "threshold": 0.8000000000000002,
    "accuracy": 1.0,
    "passed": 0.9166666666666666,
    "last_seen": "2026-04-02 15:52:25,792",
    "count": 24
  },
  {
    "symbol": "SAFE",
    "tier": "Directional",
    "probability": 0.01,
    "threshold": 0.8,
    "accuracy": 1.0,
    "passed": 0.0,
    "last_seen": "2026-04-02 15:52:25,714",
    "count": 21
  },
  {
    "symbol": "BLAST",
    "tier": "Directional",
    "probability": 0.165,
    "threshold": 0.7526707810172378,
    "accuracy": 0.9408384762715472,
    "passed": 0.0,
    "last_seen": "2026-04-02 15:52:25,707",
    "count": 22
  },
  {
    "symbol": "NMR",
    "tier": "Directional",
    "probability": 0.98,
    "threshold": 0.8000000000000002,
    "accuracy": 1.0,
    "passed": 1.0,
    "last_seen": "2026-04-02 15:52:25,632",
    "count": 24
  },
  {
    "symbol": "IOTX",
    "tier": "Directional",
    "probability": 0.8758333333333334,
    "threshold": 0.8000000000000002,
    "accuracy": 1.0,
    "passed": 1.0,
    "last_seen": "2026-04-02 15:52:25,548",
    "count": 24
  },
  {
    "symbol": "CLV",
    "tier": "Directional",
    "probability": 0.98875,
    "threshold": 0.7707582454947297,
    "accuracy": 0.963447806868412,
    "passed": 1.0,
    "last_seen": "2026-04-02 15:52:25,068",
    "count": 24
  },
  {
    "symbol": "INV",
    "tier": "Directional",
    "probability": 0.049090909090909095,
    "threshold": 0.8,
    "accuracy": 1.0,
    "passed": 0.0,
    "last_seen": "2026-04-02 15:51:52,120",
    "count": 22
  },
  {
    "symbol": "CTX",
    "tier": "Imbalance",
    "probability": 0.0,
    "threshold": 0.8,
    "accuracy": 1.0,
    "passed": 0.0,
    "last_seen": "2026-04-02 15:50:55,117",
    "count": 18
  },
  {
    "symbol": "CTX",
    "tier": "Directional",
    "probability": 0.8016666666666666,
    "threshold": 0.7675324675324675,
    "accuracy": 0.9594155844155845,
    "passed": 1.0,
    "last_seen": "2026-04-02 15:50:52,896",
    "count": 18
  },
  {
    "symbol": "CRV",
    "tier": "Directional",
    "probability": 0.03958333333333334,
    "threshold": 0.7834697855750488,
    "accuracy": 0.979337231968811,
    "passed": 0.0,
    "last_seen": "2026-04-02 15:50:52,885",
    "count": 24
  },
  {
    "symbol": "ZRO",
    "tier": "Directional",
    "probability": 0.03826086956521739,
    "threshold": 0.8,
    "accuracy": 1.0,
    "passed": 0.0,
    "last_seen": "2026-04-02 15:50:52,083",
    "count": 23
  },
  {
    "symbol": "BADGER",
    "tier": "Directional",
    "probability": 0.01391304347826087,
    "threshold": 0.7403579766536964,
    "accuracy": 0.9254474708171206,
    "passed": 0.0,
    "last_seen": "2026-04-02 15:50:51,520",
    "count": 23
  },
  {
    "symbol": "ZRX",
    "tier": "Directional",
    "probability": 0.01894736842105263,
    "threshold": 0.8,
    "accuracy": 1.0,
    "passed": 0.0,
    "last_seen": "2026-04-02 15:50:51,431",
    "count": 19
  },
  {
    "symbol": "ALT",
    "tier": "Directional",
    "probability": 0.9175000000000001,
    "threshold": 0.8,
    "accuracy": 1.0,
    "passed": 1.0,
    "last_seen": "2026-04-02 15:50:50,712",
    "count": 20
  },
  {
    "symbol": "CGLD",
    "tier": "Generalist",
    "probability": 0.4905555555555556,
    "threshold": 0.75,
    "accuracy": 1.0,
    "passed": 0.0,
    "last_seen": "2026-04-02 15:49:48,867",
    "count": 18
  },
  {
    "symbol": "CGLD",
    "tier": "Crash",
    "probability": 0.0,
    "threshold": 0.35,
    "accuracy": 1.0,
    "passed": 1.0,
    "last_seen": "2026-04-02 15:49:45,958",
    "count": 18
  },
  {
    "symbol": "ROSE",
    "tier": "Imbalance",
    "probability": 0.0,
    "threshold": 0.8000000000000002,
    "accuracy": 1.0,
    "passed": 0.0,
    "last_seen": "2026-04-02 15:49:45,488",
    "count": 24
  },
  {
    "symbol": "MASK",
    "tier": "Directional",
    "probability": 0.12166666666666666,
    "threshold": 0.8,
    "accuracy": 1.0,
    "passed": 0.0,
    "last_seen": "2026-04-02 15:49:45,451",
    "count": 18
  },
  {
    "symbol": "ORCA",
    "tier": "Directional",
    "probability": 0.20615384615384616,
    "threshold": 0.8,
    "accuracy": 1.0,
    "passed": 0.0,
    "last_seen": "2026-04-02 15:49:45,112",
    "count": 13
  },
  {
    "symbol": "ROSE",
    "tier": "Directional",
    "probability": 0.9899999999999999,
    "threshold": 0.8000000000000002,
    "accuracy": 1.0,
    "passed": 1.0,
    "last_seen": "2026-04-02 15:49:44,910",
    "count": 24
  },
  {
    "symbol": "CGLD",
    "tier": "Imbalance",
    "probability": 1.0,
    "threshold": 0.8,
    "accuracy": 1.0,
    "passed": 1.0,
    "last_seen": "2026-04-02 15:49:44,901",
    "count": 18
  },
  {
    "symbol": "ALICE",
    "tier": "Directional",
    "probability": 0.029444444444444447,
    "threshold": 0.7672080433101316,
    "accuracy": 0.9590100541376645,
    "passed": 0.0,
    "last_seen": "2026-04-02 15:49:44,772",
    "count": 18
  },
  {
    "symbol": "CGLD",
    "tier": "Directional",
    "probability": 0.9588888888888888,
    "threshold": 0.775456102464815,
    "accuracy": 0.9693201280810188,
    "passed": 1.0,
    "last_seen": "2026-04-02 15:49:44,767",
    "count": 18
  },
  {
    "symbol": "ICP",
    "tier": "Crash",
    "probability": 0.9914285714285714,
    "threshold": 0.35,
    "accuracy": 0.0,
    "passed": 0.0,
    "last_seen": "2026-04-02 15:49:18,499",
    "count": 14
  },
  {
    "symbol": "EIGEN",
    "tier": "Directional",
    "probability": 0.9473333333333332,
    "threshold": 0.7263774912075031,
    "accuracy": 0.9079718640093788,
    "passed": 1.0,
    "last_seen": "2026-04-02 15:49:16,698",
    "count": 15
  },
  {
    "symbol": "ICP",
    "tier": "Imbalance",
    "probability": 1.0,
    "threshold": 0.8,
    "accuracy": 1.0,
    "passed": 1.0,
    "last_seen": "2026-04-02 15:49:16,612",
    "count": 14
  },
  {
    "symbol": "FET",
    "tier": "Directional",
    "probability": 0.05230769230769231,
    "threshold": 0.7707213578500708,
    "accuracy": 0.9634016973125884,
    "passed": 0.0,
    "last_seen": "2026-04-02 15:49:16,530",
    "count": 26
  },
  {
    "symbol": "ICP",
    "tier": "Directional",
    "probability": 0.8478571428571428,
    "threshold": 0.7780130660058573,
    "accuracy": 0.9725163325073216,
    "passed": 1.0,
    "last_seen": "2026-04-02 15:49:16,187",
    "count": 14
  },
  {
    "symbol": "BNT",
    "tier": "Directional",
    "probability": 0.032,
    "threshold": 0.7913846153846155,
    "accuracy": 0.9892307692307692,
    "passed": 0.0,
    "last_seen": "2026-04-02 15:49:15,677",
    "count": 25
  },
  {
    "symbol": "AIOZ",
    "tier": "Directional",
    "probability": 0.013333333333333334,
    "threshold": 0.758311111111111,
    "accuracy": 0.9478888888888889,
    "passed": 0.0,
    "last_seen": "2026-04-02 15:47:39,759",
    "count": 24
  },
  {
    "symbol": "DEGEN",
    "tier": "Directional",
    "probability": 0.9833333333333333,
    "threshold": 0.7330821401657875,
    "accuracy": 0.9163526752072344,
    "passed": 1.0,
    "last_seen": "2026-04-02 15:46:49,895",
    "count": 30
  },
  {
    "symbol": "VARA",
    "tier": "Directional",
    "probability": 0.045789473684210526,
    "threshold": 0.8,
    "accuracy": 1.0,
    "passed": 0.0,
    "last_seen": "2026-04-02 15:46:40,736",
    "count": 19
  },
  {
    "symbol": "PIRATE",
    "tier": "Directional",
    "probability": 0.16,
    "threshold": 0.8,
    "accuracy": 1.0,
    "passed": 0.0,
    "last_seen": "2026-04-02 15:46:05,802",
    "count": 11
  },
  {
    "symbol": "FAI",
    "tier": "Directional",
    "probability": 0.9368421052631579,
    "threshold": 0.8,
    "accuracy": 1.0,
    "passed": 0.9473684210526315,
    "last_seen": "2026-04-02 15:45:58,076",
    "count": 19
  },
  {
    "symbol": "CTSI",
    "tier": "Directional",
    "probability": 0.15,
    "threshold": 0.791111773916934,
    "accuracy": 0.9888897173961673,
    "passed": 0.0,
    "last_seen": "2026-04-02 15:45:58,065",
    "count": 18
  },
  {
    "symbol": "BNKR",
    "tier": "Directional",
    "probability": 0.3,
    "threshold": 0.8,
    "accuracy": 1.0,
    "passed": 0.0,
    "last_seen": "2026-04-02 15:45:58,031",
    "count": 18
  },
  {
    "symbol": "UMA",
    "tier": "Directional",
    "probability": 0.025714285714285714,
    "threshold": 0.8,
    "accuracy": 1.0,
    "passed": 0.0,
    "last_seen": "2026-04-02 15:45:57,375",
    "count": 28
  },
  {
    "symbol": "ALEPH",
    "tier": "Generalist",
    "probability": 0.6625,
    "threshold": 0.5422740524781341,
    "accuracy": 0.7230320699708455,
    "passed": 1.0,
    "last_seen": "2026-04-02 15:44:46,108",
    "count": 16
  },
  {
    "symbol": "SUPER",
    "tier": "Generalist",
    "probability": 0.42800000000000005,
    "threshold": 0.75,
    "accuracy": 1.0,
    "passed": 0.0,
    "last_seen": "2026-04-02 15:44:43,241",
    "count": 10
  },
  {
    "symbol": "ALEPH",
    "tier": "Crash",
    "probability": 0.04,
    "threshold": 0.35,
    "accuracy": 1.0,
    "passed": 1.0,
    "last_seen": "2026-04-02 15:44:42,792",
    "count": 16
  },
  {
    "symbol": "ALEPH",
    "tier": "Imbalance",
    "probability": 1.0,
    "threshold": 0.8,
    "accuracy": 1.0,
    "passed": 1.0,
    "last_seen": "2026-04-02 15:44:35,964",
    "count": 16
  },
  {
    "symbol": "ALEPH",
    "tier": "Directional",
    "probability": 0.95,
    "threshold": 0.7549151091453845,
    "accuracy": 0.9436438864317306,
    "passed": 1.0,
    "last_seen": "2026-04-02 15:44:23,752",
    "count": 16
  },
  {
    "symbol": "SUPER",
    "tier": "Crash",
    "probability": 0.0,
    "threshold": 0.35,
    "accuracy": 1.0,
    "passed": 1.0,
    "last_seen": "2026-04-02 15:44:23,664",
    "count": 10
  },
  {
    "symbol": "BONK",
    "tier": "Directional",
    "probability": 0.020454545454545454,
    "threshold": 0.7541092112520684,
    "accuracy": 0.9426365140650858,
    "passed": 0.0,
    "last_seen": "2026-04-02 15:44:22,991",
    "count": 22
  },
  {
    "symbol": "FORT",
    "tier": "Directional",
    "probability": 0.045294117647058825,
    "threshold": 0.8,
    "accuracy": 1.0,
    "passed": 0.0,
    "last_seen": "2026-04-02 15:44:21,269",
    "count": 17
  },
  {
    "symbol": "REQ",
    "tier": "Directional",
    "probability": 0.01411764705882353,
    "threshold": 0.8,
    "accuracy": 1.0,
    "passed": 0.0,
    "last_seen": "2026-04-02 15:44:19,525",
    "count": 17
  },
  {
    "symbol": "GIGA",
    "tier": "Directional",
    "probability": 0.2623809523809524,
    "threshold": 0.7211022480058014,
    "accuracy": 0.9013778100072516,
    "passed": 0.0,
    "last_seen": "2026-04-02 15:44:19,093",
    "count": 21
  },
  {
    "symbol": "GFI",
    "tier": "Directional",
    "probability": 0.05,
    "threshold": 0.7708086785009862,
    "accuracy": 0.9635108481262328,
    "passed": 0.0,
    "last_seen": "2026-04-02 15:44:19,041",
    "count": 18
  },
  {
    "symbol": "SUPER",
    "tier": "Imbalance",
    "probability": 1.0,
    "threshold": 0.8,
    "accuracy": 1.0,
    "passed": 1.0,
    "last_seen": "2026-04-02 15:44:18,862",
    "count": 10
  },
  {
    "symbol": "SUPER",
    "tier": "Directional",
    "probability": 1.0,
    "threshold": 0.8,
    "accuracy": 1.0,
    "passed": 1.0,
    "last_seen": "2026-04-02 15:44:16,860",
    "count": 10
  },
  {
    "symbol": "PAX",
    "tier": "Directional",
    "probability": 0.0010526315789473684,
    "threshold": 0.8,
    "accuracy": 1.0,
    "passed": 0.0,
    "last_seen": "2026-04-02 15:44:15,864",
    "count": 19
  },
  {
    "symbol": "LOKA",
    "tier": "Generalist",
    "probability": 0.6190476190476191,
    "threshold": 0.75,
    "accuracy": 1.0,
    "passed": 0.0,
    "last_seen": "2026-04-02 15:43:01,769",
    "count": 21
  },
  {
    "symbol": "LOKA",
    "tier": "Crash",
    "probability": 0.0014285714285714286,
    "threshold": 0.35,
    "accuracy": 1.0,
    "passed": 1.0,
    "last_seen": "2026-04-02 15:42:55,190",
    "count": 21
  },
  {
    "symbol": "LOKA",
    "tier": "Imbalance",
    "probability": 1.0,
    "threshold": 0.8,
    "accuracy": 1.0,
    "passed": 1.0,
    "last_seen": "2026-04-02 15:42:49,329",
    "count": 21
  },
  {
    "symbol": "TRB",
    "tier": "Imbalance",
    "probability": 0.0,
    "threshold": 0.8000000000000002,
    "accuracy": 1.0,
    "passed": 0.0,
    "last_seen": "2026-04-02 15:42:40,234",
    "count": 24
  },
  {
    "symbol": "TRB",
    "tier": "Directional",
    "probability": 0.9633333333333333,
    "threshold": 0.8000000000000002,
    "accuracy": 1.0,
    "passed": 1.0,
    "last_seen": "2026-04-02 15:42:39,645",
    "count": 24
  },
  {
    "symbol": "RPL",
    "tier": "Directional",
    "probability": 0.01,
    "threshold": 0.8,
    "accuracy": 1.0,
    "passed": 0.0,
    "last_seen": "2026-04-02 15:42:39,395",
    "count": 15
  },
  {
    "symbol": "HOPR",
    "tier": "Directional",
    "probability": 0.07,
    "threshold": 0.758450959102425,
    "accuracy": 0.9480636988780312,
    "passed": 0.0,
    "last_seen": "2026-04-02 15:42:39,170",
    "count": 11
  },
  {
    "symbol": "KRL",
    "tier": "Directional",
    "probability": 0.02888888888888889,
    "threshold": 0.8,
    "accuracy": 1.0,
    "passed": 0.0,
    "last_seen": "2026-04-02 15:42:38,913",
    "count": 18
  },
  {
    "symbol": "TNSR",
    "tier": "Directional",
    "probability": 0.07703703703703704,
    "threshold": 0.8,
    "accuracy": 1.0,
    "passed": 0.0,
    "last_seen": "2026-04-02 15:42:38,752",
    "count": 27
  },
  {
    "symbol": "LOKA",
    "tier": "Directional",
    "probability": 0.9966666666666667,
    "threshold": 0.8,
    "accuracy": 1.0,
    "passed": 1.0,
    "last_seen": "2026-04-02 15:42:36,907",
    "count": 21
  },
  {
    "symbol": "COVAL",
    "tier": "Directional",
    "probability": 0.0,
    "threshold": 0.7806366047745359,
    "accuracy": 0.9757957559681699,
    "passed": 0.0,
    "last_seen": "2026-04-02 15:42:32,719",
    "count": 19
  },
  {
    "symbol": "COOKIE",
    "tier": "Directional",
    "probability": 0.8914285714285713,
    "threshold": 0.8,
    "accuracy": 1.0,
    "passed": 1.0,
    "last_seen": "2026-04-02 15:39:31,655",
    "count": 21
  },
  {
    "symbol": "C98",
    "tier": "Directional",
    "probability": 0.04,
    "threshold": 0.8,
    "accuracy": 1.0,
    "passed": 0.0,
    "last_seen": "2026-04-02 15:39:30,894",
    "count": 20
  },
  {
    "symbol": "METIS",
    "tier": "Directional",
    "probability": 0.07208333333333335,
    "threshold": 0.8000000000000002,
    "accuracy": 1.0,
    "passed": 0.0,
    "last_seen": "2026-04-02 15:39:30,531",
    "count": 24
  },
  {
    "symbol": "BOBBOB",
    "tier": "Directional",
    "probability": 0.8113793103448275,
    "threshold": 0.8,
    "accuracy": 1.0,
    "passed": 0.896551724137931,
    "last_seen": "2026-04-02 15:38:34,879",
    "count": 29
  },
  {
    "symbol": "FIDA",
    "tier": "Directional",
    "probability": 0.04916666666666667,
    "threshold": 0.768586597215266,
    "accuracy": 0.9607332465190824,
    "passed": 0.0,
    "last_seen": "2026-04-02 15:38:05,727",
    "count": 24
  },
  {
    "symbol": "DOT",
    "tier": "Directional",
    "probability": 0.03,
    "threshold": 0.7912520249942144,
    "accuracy": 0.989065031242768,
    "passed": 0.0,
    "last_seen": "2026-04-02 15:38:05,429",
    "count": 16
  },
  {
    "symbol": "CAKE",
    "tier": "Directional",
    "probability": 0.9868181818181818,
    "threshold": 0.8,
    "accuracy": 1.0,
    "passed": 1.0,
    "last_seen": "2026-04-02 15:38:03,908",
    "count": 22
  },
  {
    "symbol": "HONEY",
    "tier": "Specialist",
    "probability": 0.6681566666666666,
    "threshold": 0.75,
    "accuracy": 1.0,
    "passed": 0.04,
    "last_seen": "2026-04-02 15:37:38,658",
    "count": 25
  },
  {
    "symbol": "HONEY",
    "tier": "Generalist",
    "probability": 0.8188,
    "threshold": 0.75,
    "accuracy": 1.0,
    "passed": 1.0,
    "last_seen": "2026-04-02 15:37:31,872",
    "count": 25
  },
  {
    "symbol": "HONEY",
    "tier": "Crash",
    "probability": 0.08959999999999999,
    "threshold": 0.35,
    "accuracy": 1.0,
    "passed": 1.0,
    "last_seen": "2026-04-02 15:37:30,355",
    "count": 25
  },
  {
    "symbol": "HONEY",
    "tier": "Imbalance",
    "probability": 1.0,
    "threshold": 0.8,
    "accuracy": 1.0,
    "passed": 1.0,
    "last_seen": "2026-04-02 15:37:29,567",
    "count": 25
  },
  {
    "symbol": "FOX",
    "tier": "Imbalance",
    "probability": 0.0,
    "threshold": 0.8000000000000002,
    "accuracy": 1.0,
    "passed": 0.0,
    "last_seen": "2026-04-02 15:36:58,345",
    "count": 24
  },
  {
    "symbol": "FOX",
    "tier": "Directional",
    "probability": 0.8566666666666666,
    "threshold": 0.7507180650037794,
    "accuracy": 0.9383975812547242,
    "passed": 1.0,
    "last_seen": "2026-04-02 15:36:58,233",
    "count": 24
  },
  {
    "symbol": "BREV",
    "tier": "Directional",
    "probability": 0.8595652173913043,
    "threshold": 0.8,
    "accuracy": 1.0,
    "passed": 0.9565217391304348,
    "last_seen": "2026-04-02 15:36:57,467",
    "count": 23
  },
  {
    "symbol": "HONEY",
    "tier": "Directional",
    "probability": 1.0,
    "threshold": 0.8,
    "accuracy": 1.0,
    "passed": 1.0,
    "last_seen": "2026-04-02 15:36:57,168",
    "count": 25
  },
  {
    "symbol": "FIS",
    "tier": "Directional",
    "probability": 0.181,
    "threshold": 0.7721745104774992,
    "accuracy": 0.965218138096874,
    "passed": 0.0,
    "last_seen": "2026-04-02 15:36:18,799",
    "count": 20
  },
  {
    "symbol": "ARB",
    "tier": "Directional",
    "probability": 0.011153846153846155,
    "threshold": 0.7833396728794217,
    "accuracy": 0.9791745910992772,
    "passed": 0.0,
    "last_seen": "2026-04-02 15:36:18,474",
    "count": 26
  },
  {
    "symbol": "AUDIO",
    "tier": "Directional",
    "probability": 0.09,
    "threshold": 0.7613085311096858,
    "accuracy": 0.9516356638871072,
    "passed": 0.0,
    "last_seen": "2026-04-02 15:36:17,956",
    "count": 13
  },
  {
    "symbol": "AMP",
    "tier": "Directional",
    "probability": 0.7621739130434783,
    "threshold": 0.7709499938867834,
    "accuracy": 0.9636874923584792,
    "passed": 0.08695652173913043,
    "last_seen": "2026-04-02 15:36:17,879",
    "count": 23
  },
  {
    "symbol": "APE",
    "tier": "Directional",
    "probability": 0.025555555555555557,
    "threshold": 0.7698963497070752,
    "accuracy": 0.962370437133844,
    "passed": 0.0,
    "last_seen": "2026-04-02 15:36:17,860",
    "count": 27
  },
  {
    "symbol": "UNI",
    "tier": "Imbalance",
    "probability": 0.0,
    "threshold": 0.8,
    "accuracy": 1.0,
    "passed": 0.0,
    "last_seen": "2026-04-02 15:36:17,327",
    "count": 26
  },
  {
    "symbol": "DYP",
    "tier": "Directional",
    "probability": 0.16204347826086954,
    "threshold": 0.75725677830941,
    "accuracy": 0.9465709728867624,
    "passed": 0.0,
    "last_seen": "2026-04-02 15:36:17,317",
    "count": 23
  },
  {
    "symbol": "UNI",
    "tier": "Directional",
    "probability": 0.98,
    "threshold": 0.8,
    "accuracy": 1.0,
    "passed": 1.0,
    "last_seen": "2026-04-02 15:36:16,937",
    "count": 26
  },
  {
    "symbol": "ADA",
    "tier": "Directional",
    "probability": 0.014583333333333335,
    "threshold": 0.7883590386397078,
    "accuracy": 0.9854487982996348,
    "passed": 0.0,
    "last_seen": "2026-04-02 15:35:36,250",
    "count": 24
  },
  {
    "symbol": "GNO",
    "tier": "Imbalance",
    "probability": 0.027580261812422346,
    "threshold": 0.8,
    "accuracy": 1.0,
    "passed": 0.0,
    "last_seen": "2026-04-02 15:34:41,408",
    "count": 20
  },
  {
    "symbol": "GLM",
    "tier": "Directional",
    "probability": 0.14,
    "threshold": 0.7692886381236863,
    "accuracy": 0.9616107976546078,
    "passed": 0.0,
    "last_seen": "2026-04-02 15:34:37,428",
    "count": 16
  },
  {
    "symbol": "B3",
    "tier": "Directional",
    "probability": 0.7119999999999999,
    "threshold": 0.8,
    "accuracy": 1.0,
    "passed": 0.08,
    "last_seen": "2026-04-02 15:34:36,295",
    "count": 25
  },
  {
    "symbol": "SHIB",
    "tier": "Directional",
    "probability": 0.0,
    "threshold": 0.8,
    "accuracy": 1.0,
    "passed": 0.0,
    "last_seen": "2026-04-02 15:34:35,694",
    "count": 18
  },
  {
    "symbol": "GNO",
    "tier": "Directional",
    "probability": 0.999,
    "threshold": 0.7732816203404439,
    "accuracy": 0.9666020254255547,
    "passed": 1.0,
    "last_seen": "2026-04-02 15:34:35,295",
    "count": 20
  },
  {
    "symbol": "ETH",
    "tier": "Directional",
    "probability": 0.17307692307692307,
    "threshold": 0.797191692089097,
    "accuracy": 0.9964896151113712,
    "passed": 0.0,
    "last_seen": "2026-04-02 15:34:35,178",
    "count": 26
  },
  {
    "symbol": "COW",
    "tier": "Directional",
    "probability": 0.9459090909090908,
    "threshold": 0.7432596550886568,
    "accuracy": 0.9290745688608211,
    "passed": 1.0,
    "last_seen": "2026-04-02 15:33:49,392",
    "count": 22
  },
  {
    "symbol": "OP",
    "tier": "Directional",
    "probability": 0.11,
    "threshold": 0.8,
    "accuracy": 1.0,
    "passed": 0.0,
    "last_seen": "2026-04-02 15:33:47,449",
    "count": 13
  },
  {
    "symbol": "PUNDIX",
    "tier": "Directional",
    "probability": 0.019230769230769232,
    "threshold": 0.8,
    "accuracy": 1.0,
    "passed": 0.0,
    "last_seen": "2026-04-02 15:31:31,587",
    "count": 13
  },
  {
    "symbol": "APR",
    "tier": "Directional",
    "probability": 0.82,
    "threshold": 0.8,
    "accuracy": 1.0,
    "passed": 1.0,
    "last_seen": "2026-04-02 15:30:00,527",
    "count": 16
  },
  {
    "symbol": "EUL",
    "tier": "Directional",
    "probability": 0.9318181818181818,
    "threshold": 0.8,
    "accuracy": 1.0,
    "passed": 0.9545454545454546,
    "last_seen": "2026-04-02 15:29:40,134",
    "count": 22
  },
  {
    "symbol": "SOL",
    "tier": "Directional",
    "probability": 0.007500000000000001,
    "threshold": 0.8000000000000002,
    "accuracy": 1.0,
    "passed": 0.0,
    "last_seen": "2026-04-02 15:29:39,907",
    "count": 24
  },
  {
    "symbol": "SEAM",
    "tier": "Generalist",
    "probability": 0.3255555555555556,
    "threshold": 0.75,
    "accuracy": 1.0,
    "passed": 0.0,
    "last_seen": "2026-04-02 15:28:41,588",
    "count": 18
  },
  {
    "symbol": "SEAM",
    "tier": "Crash",
    "probability": 0.11333333333333334,
    "threshold": 0.35,
    "accuracy": 1.0,
    "passed": 1.0,
    "last_seen": "2026-04-02 15:28:32,284",
    "count": 18
  },
  {
    "symbol": "ASM",
    "tier": "Imbalance",
    "probability": 0.0,
    "threshold": 0.8,
    "accuracy": 1.0,
    "passed": 0.0,
    "last_seen": "2026-04-02 15:28:29,037",
    "count": 23
  },
  {
    "symbol": "SEAM",
    "tier": "Imbalance",
    "probability": 1.0,
    "threshold": 0.8,
    "accuracy": 1.0,
    "passed": 1.0,
    "last_seen": "2026-04-02 15:28:28,961",
    "count": 18
  },
  {
    "symbol": "ASM",
    "tier": "Directional",
    "probability": 0.8721739130434782,
    "threshold": 0.7652946778118718,
    "accuracy": 0.9566183472648396,
    "passed": 1.0,
    "last_seen": "2026-04-02 15:28:28,208",
    "count": 23
  },
  {
    "symbol": "G",
    "tier": "Directional",
    "probability": 0.13142857142857145,
    "threshold": 0.7676907829534193,
    "accuracy": 0.959613478691774,
    "passed": 0.0,
    "last_seen": "2026-04-02 15:28:28,172",
    "count": 35
  },
  {
    "symbol": "LPT",
    "tier": "Directional",
    "probability": 0.07541666666666667,
    "threshold": 0.8000000000000002,
    "accuracy": 1.0,
    "passed": 0.0,
    "last_seen": "2026-04-02 15:28:28,048",
    "count": 24
  },
  {
    "symbol": "SEAM",
    "tier": "Directional",
    "probability": 0.9894444444444443,
    "threshold": 0.8,
    "accuracy": 1.0,
    "passed": 1.0,
    "last_seen": "2026-04-02 15:28:27,758",
    "count": 18
  },
  {
    "symbol": "MKR",
    "tier": "Directional",
    "probability": 0.0004,
    "threshold": 0.8,
    "accuracy": 1.0,
    "passed": 0.0,
    "last_seen": "2026-04-02 15:28:27,753",
    "count": 25
  },
  {
    "symbol": "LRDS",
    "tier": "Directional",
    "probability": 0.062000000000000006,
    "threshold": 0.8,
    "accuracy": 1.0,
    "passed": 0.0,
    "last_seen": "2026-04-02 15:28:27,729",
    "count": 15
  },
  {
    "symbol": "COTI",
    "tier": "Directional",
    "probability": 0.014347826086956523,
    "threshold": 0.7732062281537972,
    "accuracy": 0.9665077851922466,
    "passed": 0.0,
    "last_seen": "2026-04-02 15:27:23,260",
    "count": 23
  },
  {
    "symbol": "STORJ",
    "tier": "Directional",
    "probability": 0.07047619047619048,
    "threshold": 0.8,
    "accuracy": 1.0,
    "passed": 0.0,
    "last_seen": "2026-04-02 15:27:00,295",
    "count": 21
  },
  {
    "symbol": "POWR",
    "tier": "Directional",
    "probability": 0.03315789473684211,
    "threshold": 0.8,
    "accuracy": 1.0,
    "passed": 0.0,
    "last_seen": "2026-04-02 15:27:00,185",
    "count": 19
  },
  {
    "symbol": "FLOW",
    "tier": "Directional",
    "probability": 0.1638095238095238,
    "threshold": 0.780386883210924,
    "accuracy": 0.9754836040136547,
    "passed": 0.0,
    "last_seen": "2026-04-02 15:26:59,932",
    "count": 21
  },
  {
    "symbol": "SKL",
    "tier": "Directional",
    "probability": 0.015833333333333335,
    "threshold": 0.8000000000000002,
    "accuracy": 1.0,
    "passed": 0.0,
    "last_seen": "2026-04-02 15:26:59,705",
    "count": 24
  },
  {
    "symbol": "FLUID",
    "tier": "Directional",
    "probability": 0.35000000000000003,
    "threshold": 0.8000000000000002,
    "accuracy": 1.0,
    "passed": 0.0,
    "last_seen": "2026-04-02 15:24:02,195",
    "count": 24
  },
  {
    "symbol": "TIME",
    "tier": "Directional",
    "probability": 0.15952380952380954,
    "threshold": 0.8,
    "accuracy": 1.0,
    "passed": 0.0,
    "last_seen": "2026-04-02 15:24:01,988",
    "count": 21
  },
  {
    "symbol": "ARPA",
    "tier": "Directional",
    "probability": 0.11199999999999999,
    "threshold": 0.754169318905156,
    "accuracy": 0.942711648631445,
    "passed": 0.0,
    "last_seen": "2026-04-02 15:24:01,774",
    "count": 25
  },
  {
    "symbol": "TRU",
    "tier": "Directional",
    "probability": 0.022400000000000003,
    "threshold": 0.8,
    "accuracy": 1.0,
    "passed": 0.0,
    "last_seen": "2026-04-02 15:21:27,403",
    "count": 25
  },
  {
    "symbol": "SD",
    "tier": "Directional",
    "probability": 0.09578947368421054,
    "threshold": 0.8,
    "accuracy": 1.0,
    "passed": 0.0,
    "last_seen": "2026-04-02 15:21:18,365",
    "count": 19
  },
  {
    "symbol": "KAVA",
    "tier": "Directional",
    "probability": 0.05869565217391304,
    "threshold": 0.8,
    "accuracy": 1.0,
    "passed": 0.0,
    "last_seen": "2026-04-02 15:21:18,097",
    "count": 23
  },
  {
    "symbol": "XTZ",
    "tier": "Directional",
    "probability": 0.02,
    "threshold": 0.8,
    "accuracy": 1.0,
    "passed": 0.0,
    "last_seen": "2026-04-02 15:21:17,622",
    "count": 19
  },
  {
    "symbol": "XRP",
    "tier": "Directional",
    "probability": 0.037142857142857144,
    "threshold": 0.8,
    "accuracy": 1.0,
    "passed": 0.0,
    "last_seen": "2026-04-02 15:21:17,563",
    "count": 21
  },
  {
    "symbol": "ASTER",
    "tier": "Directional",
    "probability": 0.44083333333333335,
    "threshold": 0.7719298245614036,
    "accuracy": 0.9649122807017544,
    "passed": 0.0,
    "last_seen": "2026-04-02 15:20:41,862",
    "count": 24
  },
  {
    "symbol": "AUCTION",
    "tier": "Directional",
    "probability": 0.07210526315789474,
    "threshold": 0.7764546071994567,
    "accuracy": 0.9705682589993208,
    "passed": 0.0,
    "last_seen": "2026-04-02 15:18:41,057",
    "count": 19
  },
  {
    "symbol": "BTC",
    "tier": "Directional",
    "probability": 0.024444444444444446,
    "threshold": 0.7998222288063405,
    "accuracy": 0.9997777860079256,
    "passed": 0.0,
    "last_seen": "2026-04-02 15:18:41,019",
    "count": 18
  },
  {
    "symbol": "POND",
    "tier": "Directional",
    "probability": 0.07857142857142858,
    "threshold": 0.8,
    "accuracy": 1.0,
    "passed": 0.0,
    "last_seen": "2026-04-02 15:17:47,235",
    "count": 21
  },
  {
    "symbol": "JASMY",
    "tier": "Directional",
    "probability": 0.0035000000000000005,
    "threshold": 0.7595321282090233,
    "accuracy": 0.949415160261279,
    "passed": 0.0,
    "last_seen": "2026-04-02 15:15:22,881",
    "count": 20
  },
  {
    "symbol": "ACH",
    "tier": "Directional",
    "probability": 0.02095238095238095,
    "threshold": 0.7770729219785825,
    "accuracy": 0.971341152473228,
    "passed": 0.0,
    "last_seen": "2026-04-02 15:15:20,355",
    "count": 21
  },
  {
    "symbol": "ALLO",
    "tier": "Directional",
    "probability": 0.8604761904761905,
    "threshold": 0.8,
    "accuracy": 1.0,
    "passed": 1.0,
    "last_seen": "2026-04-02 15:15:15,452",
    "count": 21
  },
  {
    "symbol": "HOME",
    "tier": "Directional",
    "probability": 0.6726923076923078,
    "threshold": 0.8,
    "accuracy": 1.0,
    "passed": 0.038461538461538464,
    "last_seen": "2026-04-02 15:15:14,738",
    "count": 26
  },
  {
    "symbol": "MATH",
    "tier": "Imbalance",
    "probability": 0.0,
    "threshold": 0.8,
    "accuracy": 1.0,
    "passed": 0.0,
    "last_seen": "2026-04-02 15:15:02,444",
    "count": 23
  },
  {
    "symbol": "MATH",
    "tier": "Directional",
    "probability": 0.957391304347826,
    "threshold": 0.8,
    "accuracy": 1.0,
    "passed": 1.0,
    "last_seen": "2026-04-02 15:14:59,416",
    "count": 23
  },
  {
    "symbol": "BLUR",
    "tier": "Directional",
    "probability": 0.2636842105263158,
    "threshold": 0.7888880501245565,
    "accuracy": 0.9861100626556955,
    "passed": 0.0,
    "last_seen": "2026-04-02 15:14:54,885",
    "count": 19
  },
  {
    "symbol": "PNG",
    "tier": "Directional",
    "probability": 0.1,
    "threshold": 0.8,
    "accuracy": 1.0,
    "passed": 0.0,
    "last_seen": "2026-04-02 15:14:54,655",
    "count": 26
  },
  {
    "symbol": "LQTY",
    "tier": "Directional",
    "probability": 0.08,
    "threshold": 0.8,
    "accuracy": 1.0,
    "passed": 0.0,
    "last_seen": "2026-04-02 15:14:54,332",
    "count": 16
  },
  {
    "symbol": "BIO",
    "tier": "Directional",
    "probability": 0.7333333333333333,
    "threshold": 0.8,
    "accuracy": 1.0,
    "passed": 0.05555555555555555,
    "last_seen": "2026-04-02 15:14:54,151",
    "count": 18
  },
  {
    "symbol": "ENS",
    "tier": "Directional",
    "probability": 0.004137931034482759,
    "threshold": 0.7760533152603637,
    "accuracy": 0.9700666440754546,
    "passed": 0.0,
    "last_seen": "2026-04-02 15:14:09,501",
    "count": 29
  },
  {
    "symbol": "NCT",
    "tier": "Directional",
    "probability": 0.02,
    "threshold": 0.8,
    "accuracy": 1.0,
    "passed": 0.0,
    "last_seen": "2026-04-02 15:14:09,321",
    "count": 20
  },
  {
    "symbol": "STX",
    "tier": "Directional",
    "probability": 0.02870967741935484,
    "threshold": 0.8,
    "accuracy": 1.0,
    "passed": 0.0,
    "last_seen": "2026-04-02 15:13:34,976",
    "count": 31
  },
  {
    "symbol": "NEAR",
    "tier": "Imbalance",
    "probability": 0.20246251470954157,
    "threshold": 0.8,
    "accuracy": 1.0,
    "passed": 0.05,
    "last_seen": "2026-04-02 15:13:34,830",
    "count": 20
  },
  {
    "symbol": "NEAR",
    "tier": "Directional",
    "probability": 0.9730000000000001,
    "threshold": 0.8,
    "accuracy": 1.0,
    "passed": 1.0,
    "last_seen": "2026-04-02 15:13:34,550",
    "count": 20
  },
  {
    "symbol": "XYO",
    "tier": "Directional",
    "probability": 0.11750000000000001,
    "threshold": 0.8,
    "accuracy": 1.0,
    "passed": 0.0,
    "last_seen": "2026-04-02 15:13:31,929",
    "count": 28
  },
  {
    "symbol": "ABT",
    "tier": "Specialist",
    "probability": 0.6672073699677171,
    "threshold": 0.75,
    "accuracy": 1.0,
    "passed": 0.0,
    "last_seen": "2026-04-02 15:12:44,248",
    "count": 21
  },
  {
    "symbol": "ABT",
    "tier": "Generalist",
    "probability": 0.6466666666666667,
    "threshold": 0.5662361623616237,
    "accuracy": 0.7549815498154981,
    "passed": 1.0,
    "last_seen": "2026-04-02 15:12:37,158",
    "count": 21
  },
  {
    "symbol": "ABT",
    "tier": "Crash",
    "probability": 0.0028571428571428576,
    "threshold": 0.35,
    "accuracy": 1.0,
    "passed": 1.0,
    "last_seen": "2026-04-02 15:12:35,476",
    "count": 21
  },
  {
    "symbol": "ABT",
    "tier": "Imbalance",
    "probability": 1.0,
    "threshold": 0.8,
    "accuracy": 1.0,
    "passed": 1.0,
    "last_seen": "2026-04-02 15:12:34,763",
    "count": 21
  },
  {
    "symbol": "ABT",
    "tier": "Directional",
    "probability": 0.9214285714285715,
    "threshold": 0.7541615416154163,
    "accuracy": 0.9427019270192702,
    "passed": 1.0,
    "last_seen": "2026-04-02 15:12:34,513",
    "count": 21
  },
  {
    "symbol": "GTC",
    "tier": "Directional",
    "probability": 0.2290909090909091,
    "threshold": 0.6771513353115728,
    "accuracy": 0.8464391691394659,
    "passed": 0.0,
    "last_seen": "2026-04-02 15:12:34,260",
    "count": 22
  },
  {
    "symbol": "HNT",
    "tier": "Generalist",
    "probability": 0.4376923076923077,
    "threshold": 0.5703745743473326,
    "accuracy": 0.7604994324631101,
    "passed": 0.0,
    "last_seen": "2026-04-02 15:11:51,562",
    "count": 13
  },
  {
    "symbol": "HNT",
    "tier": "Imbalance",
    "probability": 0.8644264405117059,
    "threshold": 0.8,
    "accuracy": 1.0,
    "passed": 0.8125,
    "last_seen": "2026-04-02 15:11:47,889",
    "count": 16
  },
  {
    "symbol": "HNT",
    "tier": "Directional",
    "probability": 0.8193750000000001,
    "threshold": 0.7589120675996832,
    "accuracy": 0.948640084499604,
    "passed": 1.0,
    "last_seen": "2026-04-02 15:11:47,556",
    "count": 16
  },
  {
    "symbol": "HBAR",
    "tier": "Directional",
    "probability": 0.0015,
    "threshold": 0.7714707065290254,
    "accuracy": 0.9643383831612816,
    "passed": 0.0,
    "last_seen": "2026-04-02 15:11:47,090",
    "count": 20
  },
  {
    "symbol": "CRO",
    "tier": "Directional",
    "probability": 0.11652173913043477,
    "threshold": 0.7851675021882708,
    "accuracy": 0.9814593777353384,
    "passed": 0.0,
    "last_seen": "2026-04-02 15:11:38,048",
    "count": 23
  },
  {
    "symbol": "ALGO",
    "tier": "Directional",
    "probability": 0.07214285714285715,
    "threshold": 0.7843604247295822,
    "accuracy": 0.9804505309119778,
    "passed": 0.0,
    "last_seen": "2026-04-02 15:11:38,013",
    "count": 28
  },
  {
    "symbol": "ELA",
    "tier": "Imbalance",
    "probability": 0.0,
    "threshold": 0.8,
    "accuracy": 1.0,
    "passed": 0.0,
    "last_seen": "2026-04-02 15:11:37,947",
    "count": 21
  },
  {
    "symbol": "ELA",
    "tier": "Directional",
    "probability": 0.9923809523809524,
    "threshold": 0.7671625929861848,
    "accuracy": 0.9589532412327312,
    "passed": 1.0,
    "last_seen": "2026-04-02 15:11:37,487",
    "count": 21
  },
  {
    "symbol": "QI",
    "tier": "Directional",
    "probability": 0.14772727272727273,
    "threshold": 0.8,
    "accuracy": 1.0,
    "passed": 0.0,
    "last_seen": "2026-04-02 15:11:37,335",
    "count": 22
  },
  {
    "symbol": "ALEO",
    "tier": "Directional",
    "probability": 1.0,
    "threshold": 0.8,
    "accuracy": 1.0,
    "passed": 1.0,
    "last_seen": "2026-04-02 15:11:37,156",
    "count": 15
  },
  {
    "symbol": "IMU",
    "tier": "Directional",
    "probability": 0.8950000000000001,
    "threshold": 0.8,
    "accuracy": 1.0,
    "passed": 0.9,
    "last_seen": "2026-04-02 15:11:10,190",
    "count": 20
  },
  {
    "symbol": "CFG",
    "tier": "Directional",
    "probability": 0.9605263157894737,
    "threshold": 0.7246298788694482,
    "accuracy": 0.9057873485868102,
    "passed": 1.0,
    "last_seen": "2026-04-02 15:10:39,621",
    "count": 19
  },
  {
    "symbol": "RAD",
    "tier": "Directional",
    "probability": 0.07636363636363637,
    "threshold": 0.8,
    "accuracy": 1.0,
    "passed": 0.0,
    "last_seen": "2026-04-02 15:08:54,194",
    "count": 22
  },
  {
    "symbol": "ZEN",
    "tier": "Imbalance",
    "probability": 0.8268077486171921,
    "threshold": 0.8,
    "accuracy": 1.0,
    "passed": 0.75,
    "last_seen": "2026-04-02 15:07:31,410",
    "count": 20
  },
  {
    "symbol": "ZEN",
    "tier": "Directional",
    "probability": 0.9685,
    "threshold": 0.8,
    "accuracy": 1.0,
    "passed": 1.0,
    "last_seen": "2026-04-02 15:07:31,180",
    "count": 20
  },
  {
    "symbol": "AKT",
    "tier": "Imbalance",
    "probability": 0.5161883844369788,
    "threshold": 0.8,
    "accuracy": 1.0,
    "passed": 0.45,
    "last_seen": "2026-04-02 15:06:55,057",
    "count": 20
  },
  {
    "symbol": "AKT",
    "tier": "Directional",
    "probability": 0.9925,
    "threshold": 0.7733070780002189,
    "accuracy": 0.9666338475002736,
    "passed": 1.0,
    "last_seen": "2026-04-02 15:06:54,720",
    "count": 20
  },
  {
    "symbol": "GUSD",
    "tier": "Directional",
    "probability": 0.1,
    "threshold": 0.8,
    "accuracy": 1.0,
    "passed": 0.0,
    "last_seen": "2026-04-02 15:05:50,608",
    "count": 17
  },
  {
    "symbol": "OCEAN",
    "tier": "Directional",
    "probability": 0.02962962962962963,
    "threshold": 0.8,
    "accuracy": 1.0,
    "passed": 0.0,
    "last_seen": "2026-04-02 15:04:19,557",
    "count": 27
  },
  {
    "symbol": "GHST",
    "tier": "Directional",
    "probability": 0.0888,
    "threshold": 0.7630799850727703,
    "accuracy": 0.9538499813409628,
    "passed": 0.0,
    "last_seen": "2026-04-02 15:03:51,614",
    "count": 25
  },
  {
    "symbol": "C1INCH",
    "tier": "Directional",
    "probability": 0.2142307692307692,
    "threshold": 0.8,
    "accuracy": 1.0,
    "passed": 0.0,
    "last_seen": "2026-04-02 15:03:32,472",
    "count": 26
  },
  {
    "symbol": "AGLD",
    "tier": "Specialist",
    "probability": 0.4429,
    "threshold": 0.75,
    "accuracy": 1.0,
    "passed": 0.0,
    "last_seen": "2026-04-02 15:02:15,412",
    "count": 20
  },
  {
    "symbol": "AGLD",
    "tier": "Generalist",
    "probability": 0.5814999999999999,
    "threshold": 0.5266903914590747,
    "accuracy": 0.7022538552787663,
    "passed": 1.0,
    "last_seen": "2026-04-02 15:02:12,530",
    "count": 20
  },
  {
    "symbol": "OMNI",
    "tier": "Generalist",
    "probability": 0.63,
    "threshold": 0.75,
    "accuracy": 1.0,
    "passed": 0.0,
    "last_seen": "2026-04-02 15:02:11,826",
    "count": 22
  },
  {
    "symbol": "ENJ",
    "tier": "Directional",
    "probability": 5.575689991636465e-06,
    "threshold": 0.7977827050997783,
    "accuracy": 0.9972283813747228,
    "passed": 0.0,
    "last_seen": "2026-04-02 15:02:11,366",
    "count": 25
  },
  {
    "symbol": "OMNI",
    "tier": "Crash",
    "probability": 0.0931818181818182,
    "threshold": 0.35,
    "accuracy": 1.0,
    "passed": 1.0,
    "last_seen": "2026-04-02 15:02:07,795",
    "count": 22
  },
  {
    "symbol": "AGLD",
    "tier": "Crash",
    "probability": 0.07200000000000001,
    "threshold": 0.35,
    "accuracy": 1.0,
    "passed": 1.0,
    "last_seen": "2026-04-02 15:02:06,568",
    "count": 20
  },
  {
    "symbol": "AGLD",
    "tier": "Imbalance",
    "probability": 1.0,
    "threshold": 0.8,
    "accuracy": 1.0,
    "passed": 1.0,
    "last_seen": "2026-04-02 15:01:59,757",
    "count": 20
  },
  {
    "symbol": "OMNI",
    "tier": "Imbalance",
    "probability": 1.0,
    "threshold": 0.8,
    "accuracy": 1.0,
    "passed": 1.0,
    "last_seen": "2026-04-02 15:01:58,969",
    "count": 22
  },
  {
    "symbol": "IDEX",
    "tier": "Imbalance",
    "probability": 0.0,
    "threshold": 0.8,
    "accuracy": 1.0,
    "passed": 0.0,
    "last_seen": "2026-04-02 15:01:58,546",
    "count": 21
  },
  {
    "symbol": "OMNI",
    "tier": "Directional",
    "probability": 0.9227272727272727,
    "threshold": 0.8,
    "accuracy": 1.0,
    "passed": 1.0,
    "last_seen": "2026-04-02 15:01:58,442",
    "count": 22
  },
  {
    "symbol": "AGLD",
    "tier": "Directional",
    "probability": 0.9389999999999998,
    "threshold": 0.7740156657963446,
    "accuracy": 0.9675195822454308,
    "passed": 1.0,
    "last_seen": "2026-04-02 15:01:58,339",
    "count": 20
  },
  {
    "symbol": "IDEX",
    "tier": "Directional",
    "probability": 0.8828571428571428,
    "threshold": 0.744055944055944,
    "accuracy": 0.93006993006993,
    "passed": 1.0,
    "last_seen": "2026-04-02 15:01:58,199",
    "count": 21
  },
  {
    "symbol": "CVX",
    "tier": "Directional",
    "probability": 0.07571428571428572,
    "threshold": 0.7631980987947717,
    "accuracy": 0.9539976234934647,
    "passed": 0.0,
    "last_seen": "2026-04-02 15:01:52,902",
    "count": 14
  },
  {
    "symbol": "TIA",
    "tier": "Directional",
    "probability": 0.007272727272727273,
    "threshold": 0.8,
    "accuracy": 1.0,
    "passed": 0.0,
    "last_seen": "2026-04-02 15:01:52,336",
    "count": 11
  },
  {
    "symbol": "YFI",
    "tier": "Directional",
    "probability": 0.021333333333333333,
    "threshold": 0.8,
    "accuracy": 1.0,
    "passed": 0.0,
    "last_seen": "2026-04-02 15:01:18,348",
    "count": 15
  },
  {
    "symbol": "AURORA",
    "tier": "Generalist",
    "probability": 0.5113333333333333,
    "threshold": 0.75,
    "accuracy": 1.0,
    "passed": 0.0,
    "last_seen": "2026-04-02 15:00:54,687",
    "count": 15
  },
  {
    "symbol": "AURORA",
    "tier": "Crash",
    "probability": 0.0,
    "threshold": 0.35,
    "accuracy": 1.0,
    "passed": 1.0,
    "last_seen": "2026-04-02 15:00:51,869",
    "count": 15
  },
  {
    "symbol": "AURORA",
    "tier": "Imbalance",
    "probability": 1.0,
    "threshold": 0.8,
    "accuracy": 1.0,
    "passed": 1.0,
    "last_seen": "2026-04-02 15:00:51,132",
    "count": 15
  },
  {
    "symbol": "AURORA",
    "tier": "Directional",
    "probability": 0.98,
    "threshold": 0.8,
    "accuracy": 1.0,
    "passed": 1.0,
    "last_seen": "2026-04-02 15:00:39,577",
    "count": 15
  },
  {
    "symbol": "IMX",
    "tier": "Imbalance",
    "probability": 0.0,
    "threshold": 0.8,
    "accuracy": 1.0,
    "passed": 0.0,
    "last_seen": "2026-04-02 15:00:38,570",
    "count": 16
  },
  {
    "symbol": "IMX",
    "tier": "Directional",
    "probability": 0.8825000000000001,
    "threshold": 0.8,
    "accuracy": 1.0,
    "passed": 1.0,
    "last_seen": "2026-04-02 15:00:35,061",
    "count": 16
  },
  {
    "symbol": "PRIME",
    "tier": "Imbalance",
    "probability": 0.24906194077896068,
    "threshold": 0.8,
    "accuracy": 1.0,
    "passed": 0.17391304347826086,
    "last_seen": "2026-04-02 15:00:32,750",
    "count": 23
  },
  {
    "symbol": "PRIME",
    "tier": "Directional",
    "probability": 0.97,
    "threshold": 0.8,
    "accuracy": 1.0,
    "passed": 1.0,
    "last_seen": "2026-04-02 15:00:30,305",
    "count": 23
  },
  {
    "symbol": "GRT",
    "tier": "Directional",
    "probability": 0.013999999999999999,
    "threshold": 0.7802236609770454,
    "accuracy": 0.9752795762213069,
    "passed": 0.0,
    "last_seen": "2026-04-02 15:00:30,290",
    "count": 25
  },
  {
    "symbol": "AAVE",
    "tier": "Directional",
    "probability": 0.15000000000000002,
    "threshold": 0.7868948476251487,
    "accuracy": 0.9836185595314357,
    "passed": 0.0,
    "last_seen": "2026-04-02 15:00:29,893",
    "count": 17
  },
  {
    "symbol": "BICO",
    "tier": "Directional",
    "probability": 0.17703703703703705,
    "threshold": 0.7722273143904675,
    "accuracy": 0.9652841429880844,
    "passed": 0.0,
    "last_seen": "2026-04-02 15:00:28,779",
    "count": 27
  },
  {
    "symbol": "ETHFI",
    "tier": "Directional",
    "probability": 0.9725,
    "threshold": 0.7229980276134121,
    "accuracy": 0.9037475345167651,
    "passed": 1.0,
    "last_seen": "2026-04-02 14:59:48,078",
    "count": 16
  },
  {
    "symbol": "KARRAT",
    "tier": "Generalist",
    "probability": 0.7046153846153846,
    "threshold": 0.75,
    "accuracy": 1.0,
    "passed": 0.0,
    "last_seen": "2026-04-02 14:59:04,135",
    "count": 26
  },
  {
    "symbol": "KARRAT",
    "tier": "Crash",
    "probability": 0.02230769230769231,
    "threshold": 0.35,
    "accuracy": 1.0,
    "passed": 1.0,
    "last_seen": "2026-04-02 14:58:51,793",
    "count": 26
  },
  {
    "symbol": "MUSE",
    "tier": "Crash",
    "probability": 0.998695652173913,
    "threshold": 0.35,
    "accuracy": 0.0,
    "passed": 0.0,
    "last_seen": "2026-04-02 14:58:50,647",
    "count": 23
  },
  {
    "symbol": "BAT",
    "tier": "Imbalance",
    "probability": 0.2606385585942153,
    "threshold": 0.8,
    "accuracy": 1.0,
    "passed": 0.045454545454545456,
    "last_seen": "2026-04-02 14:58:49,060",
    "count": 22
  },
  {
    "symbol": "BAT",
    "tier": "Directional",
    "probability": 0.9309090909090909,
    "threshold": 0.7811376612391626,
    "accuracy": 0.9764220765489532,
    "passed": 1.0,
    "last_seen": "2026-04-02 14:58:45,899",
    "count": 22
  },
  {
    "symbol": "AXL",
    "tier": "Directional",
    "probability": 0.09277777777777778,
    "threshold": 0.8,
    "accuracy": 1.0,
    "passed": 0.0,
    "last_seen": "2026-04-02 14:58:45,392",
    "count": 36
  },
  {
    "symbol": "MUSE",
    "tier": "Imbalance",
    "probability": 1.0,
    "threshold": 0.8,
    "accuracy": 1.0,
    "passed": 1.0,
    "last_seen": "2026-04-02 14:58:42,050",
    "count": 23
  },
  {
    "symbol": "KARRAT",
    "tier": "Imbalance",
    "probability": 1.0,
    "threshold": 0.8,
    "accuracy": 1.0,
    "passed": 1.0,
    "last_seen": "2026-04-02 14:58:41,216",
    "count": 26
  },
  {
    "symbol": "LSETH",
    "tier": "Directional",
    "probability": 0.003,
    "threshold": 0.8,
    "accuracy": 1.0,
    "passed": 0.0,
    "last_seen": "2026-04-02 14:58:40,110",
    "count": 20
  },
  {
    "symbol": "KARRAT",
    "tier": "Directional",
    "probability": 0.9976923076923078,
    "threshold": 0.8,
    "accuracy": 1.0,
    "passed": 1.0,
    "last_seen": "2026-04-02 14:58:40,008",
    "count": 26
  },
  {
    "symbol": "MUSE",
    "tier": "Directional",
    "probability": 0.9739130434782608,
    "threshold": 0.8,
    "accuracy": 1.0,
    "passed": 1.0,
    "last_seen": "2026-04-02 14:58:37,633",
    "count": 23
  },
  {
    "symbol": "MAGIC",
    "tier": "Generalist",
    "probability": 0.3477777777777778,
    "threshold": 0.75,
    "accuracy": 1.0,
    "passed": 0.0,
    "last_seen": "2026-04-02 14:57:18,975",
    "count": 18
  },
  {
    "symbol": "DOGE",
    "tier": "Directional",
    "probability": 0.16136363636363638,
    "threshold": 0.790535453637551,
    "accuracy": 0.9881693170469389,
    "passed": 0.0,
    "last_seen": "2026-04-02 14:57:12,988",
    "count": 22
  },
  {
    "symbol": "GST",
    "tier": "Directional",
    "probability": 0.03315789473684211,
    "threshold": 0.7625470107638439,
    "accuracy": 0.9531837634548048,
    "passed": 0.0,
    "last_seen": "2026-04-02 14:57:12,528",
    "count": 19
  },
  {
    "symbol": "OXT",
    "tier": "Directional",
    "probability": 0.1335714285714286,
    "threshold": 0.8,
    "accuracy": 1.0,
    "passed": 0.0,
    "last_seen": "2026-04-02 14:57:12,471",
    "count": 14
  },
  {
    "symbol": "MAGIC",
    "tier": "Crash",
    "probability": 0.0,
    "threshold": 0.35,
    "accuracy": 1.0,
    "passed": 1.0,
    "last_seen": "2026-04-02 14:57:12,011",
    "count": 18
  },
  {
    "symbol": "MAGIC",
    "tier": "Imbalance",
    "probability": 1.0,
    "threshold": 0.8,
    "accuracy": 1.0,
    "passed": 1.0,
    "last_seen": "2026-04-02 14:57:10,109",
    "count": 18
  },
  {
    "symbol": "SUI",
    "tier": "Directional",
    "probability": 0.041304347826086954,
    "threshold": 0.8,
    "accuracy": 1.0,
    "passed": 0.0,
    "last_seen": "2026-04-02 14:57:09,780",
    "count": 23
  },
  {
    "symbol": "BAND",
    "tier": "Directional",
    "probability": 0.042608695652173914,
    "threshold": 0.783645962035269,
    "accuracy": 0.9795574525440862,
    "passed": 0.0,
    "last_seen": "2026-04-02 14:57:09,470",
    "count": 23
  },
  {
    "symbol": "MAGIC",
    "tier": "Directional",
    "probability": 0.9600000000000001,
    "threshold": 0.8,
    "accuracy": 1.0,
    "passed": 1.0,
    "last_seen": "2026-04-02 14:57:08,898",
    "count": 18
  },
  {
    "symbol": "BIRB",
    "tier": "Directional",
    "probability": 0.84,
    "threshold": 0.8,
    "accuracy": 1.0,
    "passed": 1.0,
    "last_seen": "2026-04-02 14:57:04,037",
    "count": 13
  },
  {
    "symbol": "KSM",
    "tier": "Directional",
    "probability": 0.02,
    "threshold": 0.8,
    "accuracy": 1.0,
    "passed": 0.0,
    "last_seen": "2026-04-02 14:56:17,933",
    "count": 18
  },
  {
    "symbol": "IRYS",
    "tier": "Directional",
    "probability": 0.81,
    "threshold": 0.8,
    "accuracy": 1.0,
    "passed": 1.0,
    "last_seen": "2026-04-02 14:55:44,276",
    "count": 22
  },
  {
    "symbol": "GMT",
    "tier": "Directional",
    "probability": 0.01782608695652174,
    "threshold": 0.774076317383404,
    "accuracy": 0.967595396729255,
    "passed": 0.0,
    "last_seen": "2026-04-02 14:55:38,131",
    "count": 23
  },
  {
    "symbol": "CBETH",
    "tier": "Directional",
    "probability": 0.0,
    "threshold": 0.7930642750373693,
    "accuracy": 0.9913303437967116,
    "passed": 0.0,
    "last_seen": "2026-04-02 14:55:38,093",
    "count": 23
  },
  {
    "symbol": "FLOKI",
    "tier": "Directional",
    "probability": 0.925,
    "threshold": 0.8,
    "accuracy": 1.0,
    "passed": 1.0,
    "last_seen": "2026-04-02 14:55:37,410",
    "count": 16
  },
  {
    "symbol": "PYR",
    "tier": "Directional",
    "probability": 0.0425,
    "threshold": 0.8000000000000002,
    "accuracy": 1.0,
    "passed": 0.0,
    "last_seen": "2026-04-02 14:55:37,170",
    "count": 12
  },
  {
    "symbol": "ATH",
    "tier": "Directional",
    "probability": 0.9313636363636363,
    "threshold": 0.8,
    "accuracy": 1.0,
    "passed": 1.0,
    "last_seen": "2026-04-02 14:55:36,663",
    "count": 22
  },
  {
    "symbol": "SNX",
    "tier": "Directional",
    "probability": 0.0009523809523809524,
    "threshold": 0.8,
    "accuracy": 1.0,
    "passed": 0.0,
    "last_seen": "2026-04-02 14:55:36,143",
    "count": 21
  },
  {
    "symbol": "AVAX",
    "tier": "Directional",
    "probability": 0.25,
    "threshold": 0.7781101141021379,
    "accuracy": 0.9726376426276723,
    "passed": 0.0,
    "last_seen": "2026-04-02 14:53:54,951",
    "count": 12
  },
  {
    "symbol": "DRIFT",
    "tier": "Directional",
    "probability": 0.028,
    "threshold": 0.8,
    "accuracy": 1.0,
    "passed": 0.0,
    "last_seen": "2026-04-02 14:53:54,521",
    "count": 15
  },
  {
    "symbol": "PRO",
    "tier": "Directional",
    "probability": 0.01,
    "threshold": 0.8000000000000002,
    "accuracy": 1.0,
    "passed": 0.0,
    "last_seen": "2026-04-02 14:53:07,017",
    "count": 24
  },
  {
    "symbol": "APT",
    "tier": "Directional",
    "probability": 0.13315789473684211,
    "threshold": 0.8,
    "accuracy": 1.0,
    "passed": 0.0,
    "last_seen": "2026-04-02 14:52:29,149",
    "count": 19
  },
  {
    "symbol": "SEI",
    "tier": "Directional",
    "probability": 0.013000000000000001,
    "threshold": 0.8,
    "accuracy": 1.0,
    "passed": 0.0,
    "last_seen": "2026-04-02 14:52:29,134",
    "count": 10
  },
  {
    "symbol": "EGLD",
    "tier": "Directional",
    "probability": 0.05178571428571429,
    "threshold": 0.782568299966818,
    "accuracy": 0.9782103749585224,
    "passed": 0.0,
    "last_seen": "2026-04-02 14:52:21,710",
    "count": 28
  },
  {
    "symbol": "DIA",
    "tier": "Directional",
    "probability": 0.05,
    "threshold": 0.7788966816706795,
    "accuracy": 0.9736208520883494,
    "passed": 0.0,
    "last_seen": "2026-04-02 14:52:21,635",
    "count": 23
  },
  {
    "symbol": "OSMO",
    "tier": "Directional",
    "probability": 0.0723529411764706,
    "threshold": 0.8,
    "accuracy": 1.0,
    "passed": 0.0,
    "last_seen": "2026-04-02 14:52:21,539",
    "count": 17
  },
  {
    "symbol": "STRK",
    "tier": "Crash",
    "probability": 0.9399999999999998,
    "threshold": 0.35,
    "accuracy": 0.0,
    "passed": 0.0,
    "last_seen": "2026-04-02 14:51:45,519",
    "count": 23
  },
  {
    "symbol": "STRK",
    "tier": "Imbalance",
    "probability": 0.9978260869565218,
    "threshold": 0.8,
    "accuracy": 1.0,
    "passed": 1.0,
    "last_seen": "2026-04-02 14:51:44,430",
    "count": 23
  },
  {
    "symbol": "CVC",
    "tier": "Imbalance",
    "probability": 0.03412853228063564,
    "threshold": 0.8,
    "accuracy": 1.0,
    "passed": 0.0,
    "last_seen": "2026-04-02 14:51:34,006",
    "count": 15
  },
  {
    "symbol": "ATOM",
    "tier": "Directional",
    "probability": 0.05466666666666667,
    "threshold": 0.7870896915138874,
    "accuracy": 0.9838621143923592,
    "passed": 0.0,
    "last_seen": "2026-04-02 14:51:32,633",
    "count": 15
  },
  {
    "symbol": "ERA",
    "tier": "Directional",
    "probability": 0.5486666666666667,
    "threshold": 0.8,
    "accuracy": 1.0,
    "passed": 0.0,
    "last_seen": "2026-04-02 14:51:32,327",
    "count": 30
  },
  {
    "symbol": "CVC",
    "tier": "Directional",
    "probability": 0.912,
    "threshold": 0.7797836320092494,
    "accuracy": 0.9747295400115615,
    "passed": 1.0,
    "last_seen": "2026-04-02 14:51:32,268",
    "count": 15
  },
  {
    "symbol": "STRK",
    "tier": "Directional",
    "probability": 0.95,
    "threshold": 0.8,
    "accuracy": 1.0,
    "passed": 1.0,
    "last_seen": "2026-04-02 14:51:30,929",
    "count": 23
  },
  {
    "symbol": "HIGH",
    "tier": "Directional",
    "probability": 0.042222222222222223,
    "threshold": 0.7617166729965819,
    "accuracy": 0.9521458412457273,
    "passed": 0.0,
    "last_seen": "2026-04-02 14:50:50,947",
    "count": 18
  },
  {
    "symbol": "HYPER",
    "tier": "Directional",
    "probability": 0.36,
    "threshold": 0.8,
    "accuracy": 1.0,
    "passed": 0.0,
    "last_seen": "2026-04-02 14:50:50,690",
    "count": 15
  },
  {
    "symbol": "DBR",
    "tier": "Directional",
    "probability": 0.7716666666666667,
    "threshold": 0.8,
    "accuracy": 1.0,
    "passed": 0.0,
    "last_seen": "2026-04-02 14:49:10,205",
    "count": 18
  },
  {
    "symbol": "NKN",
    "tier": "Directional",
    "probability": 0.12653846153846154,
    "threshold": 0.8,
    "accuracy": 1.0,
    "passed": 0.0,
    "last_seen": "2026-04-02 14:47:43,696",
    "count": 26
  },
  {
    "symbol": "ENA",
    "tier": "Directional",
    "probability": 0.9892307692307691,
    "threshold": 0.8,
    "accuracy": 1.0,
    "passed": 1.0,
    "last_seen": "2026-04-02 14:47:43,686",
    "count": 13
  },
  {
    "symbol": "FIGHT",
    "tier": "Directional",
    "probability": 0.9504761904761905,
    "threshold": 0.6762886597938145,
    "accuracy": 0.845360824742268,
    "passed": 1.0,
    "last_seen": "2026-04-02 14:47:42,230",
    "count": 21
  },
  {
    "symbol": "ERN",
    "tier": "Directional",
    "probability": 0.0,
    "threshold": 0.7583498468744372,
    "accuracy": 0.9479373085930464,
    "passed": 0.0,
    "last_seen": "2026-04-02 14:47:37,587",
    "count": 12
  },
  {
    "symbol": "BLZ",
    "tier": "Directional",
    "probability": 0.045000000000000005,
    "threshold": 0.7651710824124618,
    "accuracy": 0.9564638530155772,
    "passed": 0.0,
    "last_seen": "2026-04-02 14:46:46,402",
    "count": 12
  },
  {
    "symbol": "DOOD",
    "tier": "Directional",
    "probability": 0.6175,
    "threshold": 0.8,
    "accuracy": 1.0,
    "passed": 0.0,
    "last_seen": "2026-04-02 14:46:46,306",
    "count": 16
  },
  {
    "symbol": "AKT",
    "tier": "Specialist",
    "probability": 0.3717911706349206,
    "threshold": 0.75,
    "accuracy": 1.0,
    "passed": 0.0,
    "last_seen": "2026-04-02 14:42:53,693",
    "count": 8
  },
  {
    "symbol": "PLU",
    "tier": "Imbalance",
    "probability": 0.0,
    "threshold": 0.8,
    "accuracy": 1.0,
    "passed": 0.0,
    "last_seen": "2026-04-02 14:42:52,042",
    "count": 25
  },
  {
    "symbol": "DOGINME",
    "tier": "Directional",
    "probability": 0.72,
    "threshold": 0.7186127167630059,
    "accuracy": 0.8982658959537573,
    "passed": 1.0,
    "last_seen": "2026-04-02 14:42:51,839",
    "count": 17
  },
  {
    "symbol": "PLU",
    "tier": "Directional",
    "probability": 0.9016,
    "threshold": 0.8,
    "accuracy": 1.0,
    "passed": 1.0,
    "last_seen": "2026-04-02 14:42:51,762",
    "count": 25
  },
  {
    "symbol": "AKT",
    "tier": "Generalist",
    "probability": 0.5522222222222223,
    "threshold": 0.5305486284289277,
    "accuracy": 0.7073981712385703,
    "passed": 0.8888888888888888,
    "last_seen": "2026-04-02 14:42:51,661",
    "count": 9
  },
  {
    "symbol": "AKT",
    "tier": "Crash",
    "probability": 0.0,
    "threshold": 0.35,
    "accuracy": 1.0,
    "passed": 1.0,
    "last_seen": "2026-04-02 14:42:46,623",
    "count": 9
  },
  {
    "symbol": "COMP",
    "tier": "Directional",
    "probability": 0.0010526315789473684,
    "threshold": 0.8,
    "accuracy": 1.0,
    "passed": 0.0,
    "last_seen": "2026-04-02 14:42:40,498",
    "count": 19
  },
  {
    "symbol": "GODS",
    "tier": "Directional",
    "probability": 0.10466666666666667,
    "threshold": 0.7688724192694547,
    "accuracy": 0.9610905240868184,
    "passed": 0.0,
    "last_seen": "2026-04-02 14:42:40,285",
    "count": 15
  },
  {
    "symbol": "ARKM",
    "tier": "Directional",
    "probability": 0.12125,
    "threshold": 0.7597142522543623,
    "accuracy": 0.9496428153179528,
    "passed": 0.0,
    "last_seen": "2026-04-02 14:42:39,656",
    "count": 16
  },
  {
    "symbol": "CORECHAIN",
    "tier": "Directional",
    "probability": 0.24,
    "threshold": 0.8,
    "accuracy": 1.0,
    "passed": 0.0,
    "last_seen": "2026-04-02 14:42:07,820",
    "count": 23
  },
  {
    "symbol": "ZEC",
    "tier": "Imbalance",
    "probability": 0.0,
    "threshold": 0.8,
    "accuracy": 1.0,
    "passed": 0.0,
    "last_seen": "2026-04-02 14:41:25,195",
    "count": 21
  },
  {
    "symbol": "ZEC",
    "tier": "Directional",
    "probability": 0.9990476190476191,
    "threshold": 0.8,
    "accuracy": 1.0,
    "passed": 1.0,
    "last_seen": "2026-04-02 14:41:23,811",
    "count": 21
  },
  {
    "symbol": "ZEN",
    "tier": "Generalist",
    "probability": 0.29,
    "threshold": 0.75,
    "accuracy": 1.0,
    "passed": 0.0,
    "last_seen": "2026-04-02 14:41:09,338",
    "count": 15
  },
  {
    "symbol": "INDEX",
    "tier": "Imbalance",
    "probability": 0.0,
    "threshold": 0.8,
    "accuracy": 1.0,
    "passed": 0.0,
    "last_seen": "2026-04-02 14:41:06,708",
    "count": 13
  },
  {
    "symbol": "INDEX",
    "tier": "Directional",
    "probability": 0.9907692307692307,
    "threshold": 0.8,
    "accuracy": 1.0,
    "passed": 1.0,
    "last_seen": "2026-04-02 14:41:06,554",
    "count": 13
  },
  {
    "symbol": "00",
    "tier": "Crash",
    "probability": 0.9741666666666666,
    "threshold": 0.3499999999999999,
    "accuracy": 0.0,
    "passed": 0.0,
    "last_seen": "2026-04-02 14:39:30,750",
    "count": 24
  },
  {
    "symbol": "00",
    "tier": "Imbalance",
    "probability": 1.0,
    "threshold": 0.8000000000000002,
    "accuracy": 1.0,
    "passed": 1.0,
    "last_seen": "2026-04-02 14:39:28,515",
    "count": 24
  },
  {
    "symbol": "00",
    "tier": "Directional",
    "probability": 0.98875,
    "threshold": 0.7388711395101172,
    "accuracy": 0.9235889243876464,
    "passed": 1.0,
    "last_seen": "2026-04-02 14:39:28,356",
    "count": 24
  },
  {
    "symbol": "HYPE",
    "tier": "Directional",
    "probability": 0.386,
    "threshold": 0.8,
    "accuracy": 1.0,
    "passed": 0.0,
    "last_seen": "2026-04-02 14:39:27,532",
    "count": 20
  },
  {
    "symbol": "MLN",
    "tier": "Directional",
    "probability": 0.005,
    "threshold": 0.8,
    "accuracy": 1.0,
    "passed": 0.0,
    "last_seen": "2026-04-02 14:38:42,341",
    "count": 26
  },
  {
    "symbol": "KNC",
    "tier": "Directional",
    "probability": 0.10545454545454545,
    "threshold": 0.8,
    "accuracy": 1.0,
    "passed": 0.0,
    "last_seen": "2026-04-02 14:37:16,538",
    "count": 22
  },
  {
    "symbol": "XLM",
    "tier": "Directional",
    "probability": 0.01,
    "threshold": 0.8000000000000002,
    "accuracy": 1.0,
    "passed": 0.0,
    "last_seen": "2026-04-02 14:36:06,219",
    "count": 12
  },
  {
    "symbol": "C00",
    "tier": "Crash",
    "probability": 0.9736842105263158,
    "threshold": 0.35,
    "accuracy": 0.0,
    "passed": 0.0,
    "last_seen": "2026-04-02 14:34:55,243",
    "count": 19
  },
  {
    "symbol": "C00",
    "tier": "Imbalance",
    "probability": 1.0,
    "threshold": 0.8,
    "accuracy": 1.0,
    "passed": 1.0,
    "last_seen": "2026-04-02 14:34:53,134",
    "count": 19
  },
  {
    "symbol": "C00",
    "tier": "Directional",
    "probability": 0.9910526315789473,
    "threshold": 0.8,
    "accuracy": 1.0,
    "passed": 1.0,
    "last_seen": "2026-04-02 14:34:52,923",
    "count": 19
  },
  {
    "symbol": "DEXT",
    "tier": "Directional",
    "probability": 0.3008695652173913,
    "threshold": 0.7346938775510204,
    "accuracy": 0.9183673469387756,
    "passed": 0.0,
    "last_seen": "2026-04-02 14:33:40,849",
    "count": 23
  },
  {
    "symbol": "FORTH",
    "tier": "Directional",
    "probability": 0.0668421052631579,
    "threshold": 0.7838926174496645,
    "accuracy": 0.9798657718120807,
    "passed": 0.0,
    "last_seen": "2026-04-02 14:33:03,413",
    "count": 19
  },
  {
    "symbol": "INJ",
    "tier": "Directional",
    "probability": 0.029545454545454545,
    "threshold": 0.8,
    "accuracy": 1.0,
    "passed": 0.0,
    "last_seen": "2026-04-02 14:31:34,299",
    "count": 22
  },
  {
    "symbol": "ACS",
    "tier": "Directional",
    "probability": 0.03,
    "threshold": 0.779070252240984,
    "accuracy": 0.97383781530123,
    "passed": 0.0,
    "last_seen": "2026-04-02 14:29:45,448",
    "count": 20
  },
  {
    "symbol": "FUN1",
    "tier": "Directional",
    "probability": 0.892962962962963,
    "threshold": 0.8,
    "accuracy": 1.0,
    "passed": 0.9259259259259259,
    "last_seen": "2026-04-02 14:29:44,612",
    "count": 27
  },
  {
    "symbol": "USDT",
    "tier": "Directional",
    "probability": 0.0,
    "threshold": 0.8,
    "accuracy": 1.0,
    "passed": 0.0,
    "last_seen": "2026-04-02 14:29:44,111",
    "count": 18
  },
  {
    "symbol": "LRC",
    "tier": "Directional",
    "probability": 0.1485,
    "threshold": 0.8,
    "accuracy": 1.0,
    "passed": 0.0,
    "last_seen": "2026-04-02 14:28:28,846",
    "count": 20
  },
  {
    "symbol": "LCX",
    "tier": "Directional",
    "probability": 0.07050000000000001,
    "threshold": 0.8,
    "accuracy": 1.0,
    "passed": 0.0,
    "last_seen": "2026-04-02 14:28:24,368",
    "count": 20
  },
  {
    "symbol": "MINA",
    "tier": "Imbalance",
    "probability": 0.01380124885916755,
    "threshold": 0.8,
    "accuracy": 1.0,
    "passed": 0.0,
    "last_seen": "2026-04-02 14:28:05,564",
    "count": 21
  },
  {
    "symbol": "RENDER",
    "tier": "Directional",
    "probability": 0.04,
    "threshold": 0.8,
    "accuracy": 1.0,
    "passed": 0.0,
    "last_seen": "2026-04-02 14:28:04,721",
    "count": 21
  },
  {
    "symbol": "MINA",
    "tier": "Directional",
    "probability": 0.970952380952381,
    "threshold": 0.8,
    "accuracy": 1.0,
    "passed": 1.0,
    "last_seen": "2026-04-02 14:28:04,633",
    "count": 21
  },
  {
    "symbol": "BERA",
    "tier": "Directional",
    "probability": 0.87,
    "threshold": 0.8,
    "accuracy": 1.0,
    "passed": 1.0,
    "last_seen": "2026-04-02 14:27:22,260",
    "count": 13
  },
  {
    "symbol": "SAND",
    "tier": "Directional",
    "probability": 0.0940909090909091,
    "threshold": 0.8,
    "accuracy": 1.0,
    "passed": 0.0,
    "last_seen": "2026-04-02 14:26:54,113",
    "count": 22
  },
  {
    "symbol": "SUSHI",
    "tier": "Directional",
    "probability": 0.03,
    "threshold": 0.8,
    "accuracy": 1.0,
    "passed": 0.0,
    "last_seen": "2026-04-02 14:21:52,345",
    "count": 17
  },
  {
    "symbol": "ACX",
    "tier": "Directional",
    "probability": 0.12050000000000001,
    "threshold": 0.8,
    "accuracy": 1.0,
    "passed": 0.0,
    "last_seen": "2026-04-02 14:16:22,939",
    "count": 20
  },
  {
    "symbol": "MDT",
    "tier": "Directional",
    "probability": 0.0304,
    "threshold": 0.8,
    "accuracy": 1.0,
    "passed": 0.0,
    "last_seen": "2026-04-02 14:16:22,902",
    "count": 25
  },
  {
    "symbol": "FARTCOIN",
    "tier": "Directional",
    "probability": 0.86,
    "threshold": 0.8,
    "accuracy": 1.0,
    "passed": 1.0,
    "last_seen": "2026-04-02 14:15:18,256",
    "count": 19
  },
  {
    "symbol": "RARI",
    "tier": "Generalist",
    "probability": 0.45869565217391306,
    "threshold": 0.75,
    "accuracy": 1.0,
    "passed": 0.0,
    "last_seen": "2026-04-02 14:15:16,952",
    "count": 23
  },
  {
    "symbol": "RARI",
    "tier": "Crash",
    "probability": 0.08565217391304349,
    "threshold": 0.35,
    "accuracy": 1.0,
    "passed": 1.0,
    "last_seen": "2026-04-02 14:15:13,678",
    "count": 23
  },
  {
    "symbol": "RARI",
    "tier": "Imbalance",
    "probability": 1.0,
    "threshold": 0.8,
    "accuracy": 1.0,
    "passed": 1.0,
    "last_seen": "2026-04-02 14:15:11,179",
    "count": 23
  },
  {
    "symbol": "RARI",
    "tier": "Directional",
    "probability": 0.9778260869565216,
    "threshold": 0.8,
    "accuracy": 1.0,
    "passed": 1.0,
    "last_seen": "2026-04-02 14:15:10,460",
    "count": 23
  },
  {
    "symbol": "FIL",
    "tier": "Directional",
    "probability": 0.006521739130434784,
    "threshold": 0.7831456840668715,
    "accuracy": 0.9789321050835893,
    "passed": 0.0,
    "last_seen": "2026-04-02 14:13:47,875",
    "count": 23
  },
  {
    "symbol": "BTRST",
    "tier": "Directional",
    "probability": 0.0995,
    "threshold": 0.750937950937951,
    "accuracy": 0.9386724386724389,
    "passed": 0.0,
    "last_seen": "2026-04-02 14:13:47,035",
    "count": 20
  },
  {
    "symbol": "POLS",
    "tier": "Generalist",
    "probability": 0.31277777777777777,
    "threshold": 0.75,
    "accuracy": 1.0,
    "passed": 0.0,
    "last_seen": "2026-04-02 14:09:19,089",
    "count": 18
  },
  {
    "symbol": "POLS",
    "tier": "Crash",
    "probability": 0.031111111111111107,
    "threshold": 0.35,
    "accuracy": 1.0,
    "passed": 1.0,
    "last_seen": "2026-04-02 14:09:10,601",
    "count": 18
  },
  {
    "symbol": "POLS",
    "tier": "Imbalance",
    "probability": 0.9845820105820106,
    "threshold": 0.8,
    "accuracy": 1.0,
    "passed": 1.0,
    "last_seen": "2026-04-02 14:09:06,020",
    "count": 18
  },
  {
    "symbol": "POLS",
    "tier": "Directional",
    "probability": 0.9994444444444444,
    "threshold": 0.8,
    "accuracy": 1.0,
    "passed": 1.0,
    "last_seen": "2026-04-02 14:08:56,454",
    "count": 18
  },
  {
    "symbol": "ANKR",
    "tier": "Directional",
    "probability": 0.1,
    "threshold": 0.7882156289176764,
    "accuracy": 0.9852695361470954,
    "passed": 0.0,
    "last_seen": "2026-04-02 14:07:30,762",
    "count": 22
  },
  {
    "symbol": "SPELL",
    "tier": "Directional",
    "probability": 0.0033333333333333335,
    "threshold": 0.8000000000000002,
    "accuracy": 1.0,
    "passed": 0.0,
    "last_seen": "2026-04-02 14:07:20,669",
    "count": 24
  },
  {
    "symbol": "BAL",
    "tier": "Directional",
    "probability": 0.19363636363636363,
    "threshold": 0.7647121535181237,
    "accuracy": 0.9558901918976546,
    "passed": 0.0,
    "last_seen": "2026-04-02 14:02:35,604",
    "count": 22
  },
  {
    "symbol": "NEON",
    "tier": "Imbalance",
    "probability": 0.0,
    "threshold": 0.8,
    "accuracy": 1.0,
    "passed": 0.0,
    "last_seen": "2026-04-02 13:52:36,375",
    "count": 19
  },
  {
    "symbol": "NEON",
    "tier": "Directional",
    "probability": 0.9899999999999999,
    "threshold": 0.8,
    "accuracy": 1.0,
    "passed": 1.0,
    "last_seen": "2026-04-02 13:52:34,504",
    "count": 19
  },
  {
    "symbol": "CHZ",
    "tier": "Directional",
    "probability": 0.19384615384615383,
    "threshold": 0.7876977822964988,
    "accuracy": 0.9846222278706234,
    "passed": 0.0,
    "last_seen": "2026-04-02 13:44:31,666",
    "count": 26
  },
  {
    "symbol": "DNT",
    "tier": "Generalist",
    "probability": 0.650952380952381,
    "threshold": 0.5303970223325062,
    "accuracy": 0.707196029776675,
    "passed": 1.0,
    "last_seen": "2026-04-02 13:42:46,121",
    "count": 21
  },
  {
    "symbol": "DNT",
    "tier": "Crash",
    "probability": 0.0,
    "threshold": 0.35,
    "accuracy": 1.0,
    "passed": 1.0,
    "last_seen": "2026-04-02 13:42:42,940",
    "count": 21
  },
  {
    "symbol": "DNT",
    "tier": "Imbalance",
    "probability": 1.0,
    "threshold": 0.8,
    "accuracy": 1.0,
    "passed": 1.0,
    "last_seen": "2026-04-02 13:42:41,714",
    "count": 21
  },
  {
    "symbol": "HFT",
    "tier": "Directional",
    "probability": 0.0225,
    "threshold": 0.8,
    "accuracy": 1.0,
    "passed": 0.0,
    "last_seen": "2026-04-02 13:42:41,686",
    "count": 20
  },
  {
    "symbol": "DNT",
    "tier": "Directional",
    "probability": 0.9595238095238094,
    "threshold": 0.7245009074410164,
    "accuracy": 0.9056261343012705,
    "passed": 1.0,
    "last_seen": "2026-04-02 13:42:41,513",
    "count": 21
  },
  {
    "symbol": "MSOL",
    "tier": "Directional",
    "probability": 0.14357142857142854,
    "threshold": 0.8,
    "accuracy": 1.0,
    "passed": 0.0,
    "last_seen": "2026-04-02 13:41:51,886",
    "count": 14
  },
  {
    "symbol": "PERP",
    "tier": "Directional",
    "probability": 0.29263157894736846,
    "threshold": 0.8,
    "accuracy": 1.0,
    "passed": 0.0,
    "last_seen": "2026-04-02 13:39:33,896",
    "count": 19
  },
  {
    "symbol": "JTO",
    "tier": "Directional",
    "probability": 0.19142857142857145,
    "threshold": 0.8,
    "accuracy": 1.0,
    "passed": 0.0,
    "last_seen": "2026-04-02 13:36:05,323",
    "count": 21
  },
  {
    "symbol": "ILV",
    "tier": "Directional",
    "probability": 0.0264,
    "threshold": 0.7753155680224404,
    "accuracy": 0.9691444600280505,
    "passed": 0.0,
    "last_seen": "2026-04-02 13:36:05,039",
    "count": 25
  },
  {
    "symbol": "LDO",
    "tier": "Directional",
    "probability": 0.05,
    "threshold": 0.8,
    "accuracy": 1.0,
    "passed": 0.0,
    "last_seen": "2026-04-02 13:34:29,146",
    "count": 15
  },
  {
    "symbol": "QNT",
    "tier": "Directional",
    "probability": 0.00818181818181818,
    "threshold": 0.8,
    "accuracy": 1.0,
    "passed": 0.0,
    "last_seen": "2026-04-02 13:33:05,806",
    "count": 22
  },
  {
    "symbol": "AVNT",
    "tier": "Directional",
    "probability": 0.6452380952380953,
    "threshold": 0.8,
    "accuracy": 1.0,
    "passed": 0.0,
    "last_seen": "2026-04-02 13:29:37,368",
    "count": 21
  },
  {
    "symbol": "PRIME",
    "tier": "Generalist",
    "probability": 0.43,
    "threshold": 0.75,
    "accuracy": 1.0,
    "passed": 0.0,
    "last_seen": "2026-04-02 13:28:15,867",
    "count": 4
  },
  {
    "symbol": "PRIME",
    "tier": "Crash",
    "probability": 0.08,
    "threshold": 0.35,
    "accuracy": 1.0,
    "passed": 1.0,
    "last_seen": "2026-04-02 13:28:12,116",
    "count": 4
  },
  {
    "symbol": "RONIN",
    "tier": "Directional",
    "probability": 0.14736842105263157,
    "threshold": 0.8,
    "accuracy": 1.0,
    "passed": 0.0,
    "last_seen": "2026-04-02 13:28:08,315",
    "count": 19
  },
  {
    "symbol": "ZETA",
    "tier": "Directional",
    "probability": 0.04882352941176471,
    "threshold": 0.8,
    "accuracy": 1.0,
    "passed": 0.0,
    "last_seen": "2026-04-02 13:26:22,778",
    "count": 17
  },
  {
    "symbol": "VTHO",
    "tier": "Directional",
    "probability": 0.028333333333333335,
    "threshold": 0.8,
    "accuracy": 1.0,
    "passed": 0.0,
    "last_seen": "2026-04-02 13:24:46,835",
    "count": 18
  },
  {
    "symbol": "VOXEL",
    "tier": "Directional",
    "probability": 0.1742857142857143,
    "threshold": 0.8,
    "accuracy": 1.0,
    "passed": 0.0,
    "last_seen": "2026-04-02 13:14:52,196",
    "count": 28
  },
  {
    "symbol": "ALCX",
    "tier": "Generalist",
    "probability": 0.4441176470588235,
    "threshold": 0.5725334448160535,
    "accuracy": 0.7633779264214047,
    "passed": 0.0,
    "last_seen": "2026-04-02 13:10:09,425",
    "count": 17
  },
  {
    "symbol": "ALCX",
    "tier": "Crash",
    "probability": 0.001764705882352941,
    "threshold": 0.35,
    "accuracy": 1.0,
    "passed": 1.0,
    "last_seen": "2026-04-02 13:09:54,763",
    "count": 17
  },
  {
    "symbol": "ALCX",
    "tier": "Imbalance",
    "probability": 1.0,
    "threshold": 0.8,
    "accuracy": 1.0,
    "passed": 1.0,
    "last_seen": "2026-04-02 13:09:54,007",
    "count": 17
  },
  {
    "symbol": "ALCX",
    "tier": "Directional",
    "probability": 0.9194117647058824,
    "threshold": 0.7795302013422819,
    "accuracy": 0.9744127516778524,
    "passed": 1.0,
    "last_seen": "2026-04-02 13:09:53,088",
    "count": 17
  },
  {
    "symbol": "AST",
    "tier": "Specialist",
    "probability": 0.74,
    "threshold": 0.75,
    "accuracy": 1.0,
    "passed": 0.2857142857142857,
    "last_seen": "2026-04-02 13:09:07,736",
    "count": 14
  },
  {
    "symbol": "API3",
    "tier": "Directional",
    "probability": 0.07133333333333333,
    "threshold": 0.7688750555802579,
    "accuracy": 0.9610938194753224,
    "passed": 0.0,
    "last_seen": "2026-04-02 13:09:06,742",
    "count": 15
  },
  {
    "symbol": "AST",
    "tier": "Generalist",
    "probability": 0.6128571428571429,
    "threshold": 0.47939866369710465,
    "accuracy": 0.6391982182628062,
    "passed": 1.0,
    "last_seen": "2026-04-02 13:09:05,968",
    "count": 14
  },
  {
    "symbol": "AST",
    "tier": "Crash",
    "probability": 0.019285714285714288,
    "threshold": 0.35,
    "accuracy": 1.0,
    "passed": 1.0,
    "last_seen": "2026-04-02 13:08:12,788",
    "count": 14
  },
  {
    "symbol": "AST",
    "tier": "Imbalance",
    "probability": 1.0,
    "threshold": 0.8,
    "accuracy": 1.0,
    "passed": 1.0,
    "last_seen": "2026-04-02 13:08:11,513",
    "count": 14
  },
  {
    "symbol": "AST",
    "tier": "Directional",
    "probability": 0.8971428571428571,
    "threshold": 0.7454315013250374,
    "accuracy": 0.9317893766562968,
    "passed": 1.0,
    "last_seen": "2026-04-02 13:08:11,254",
    "count": 14
  },
  {
    "symbol": "RARE",
    "tier": "Directional",
    "probability": 0.02375,
    "threshold": 0.8,
    "accuracy": 1.0,
    "passed": 0.0,
    "last_seen": "2026-04-02 13:05:16,196",
    "count": 16
  },
  {
    "symbol": "SPA",
    "tier": "Crash",
    "probability": 0.9,
    "threshold": 0.35,
    "accuracy": 0.0,
    "passed": 0.0,
    "last_seen": "2026-04-02 13:00:14,088",
    "count": 1
  },
  {
    "symbol": "EUROC",
    "tier": "Directional",
    "probability": 0.004285714285714286,
    "threshold": 0.8,
    "accuracy": 1.0,
    "passed": 0.0,
    "last_seen": "2026-04-02 12:47:09,403",
    "count": 14
  },
  {
    "symbol": "ELSA",
    "tier": "Directional",
    "probability": 0.8176470588235294,
    "threshold": 0.8,
    "accuracy": 1.0,
    "passed": 1.0,
    "last_seen": "2026-04-02 12:42:24,599",
    "count": 17
  },
  {
    "symbol": "A8",
    "tier": "Directional",
    "probability": 0.16772727272727272,
    "threshold": 0.7407407407407409,
    "accuracy": 0.925925925925926,
    "passed": 0.0,
    "last_seen": "2026-04-02 12:30:58,722",
    "count": 22
  },
  {
    "symbol": "AMP",
    "tier": "Imbalance",
    "probability": 0.0,
    "threshold": 0.8,
    "accuracy": 1.0,
    "passed": 0.0,
    "last_seen": "2026-04-02 12:23:09,746",
    "count": 2
  },
  {
    "symbol": "DESO",
    "tier": "Directional",
    "probability": 0.03558215958329654,
    "threshold": 0.7841959183673469,
    "accuracy": 0.9802448979591836,
    "passed": 0.0,
    "last_seen": "2026-04-02 12:20:19,873",
    "count": 21
  },
  {
    "symbol": "OGN",
    "tier": "Directional",
    "probability": 0.044444444444444446,
    "threshold": 0.8,
    "accuracy": 1.0,
    "passed": 0.0,
    "last_seen": "2026-04-02 11:55:25,180",
    "count": 18
  },
  {
    "symbol": "FARM",
    "tier": "Directional",
    "probability": 0.07,
    "threshold": 0.7731268011527378,
    "accuracy": 0.9664085014409222,
    "passed": 0.0,
    "last_seen": "2026-04-02 10:57:44,302",
    "count": 13
  },
  {
    "symbol": "SUKU",
    "tier": "Generalist",
    "probability": 0.545,
    "threshold": 0.75,
    "accuracy": 1.0,
    "passed": 0.0,
    "last_seen": "2026-04-02 08:57:07,976",
    "count": 2
  },
  {
    "symbol": "NEAR",
    "tier": "Generalist",
    "probability": 0.35,
    "threshold": 0.75,
    "accuracy": 1.0,
    "passed": 0.0,
    "last_seen": "2026-04-02 07:46:56,937",
    "count": 1
  },
  {
    "symbol": "NEAR",
    "tier": "Crash",
    "probability": 0.0,
    "threshold": 0.35,
    "accuracy": 1.0,
    "passed": 1.0,
    "last_seen": "2026-04-02 07:46:28,099",
    "count": 1
  },
  {
    "symbol": "BAT",
    "tier": "Specialist",
    "probability": 0.0,
    "threshold": 0.75,
    "accuracy": 1.0,
    "passed": 0.0,
    "last_seen": "2026-04-02 06:59:07,163",
    "count": 1
  },
  {
    "symbol": "BAT",
    "tier": "Generalist",
    "probability": 0.62,
    "threshold": 0.5217391304347826,
    "accuracy": 0.6956521739130435,
    "passed": 1.0,
    "last_seen": "2026-04-02 06:59:06,728",
    "count": 1
  },
  {
    "symbol": "BAT",
    "tier": "Crash",
    "probability": 0.0,
    "threshold": 0.35,
    "accuracy": 1.0,
    "passed": 1.0,
    "last_seen": "2026-04-02 06:59:03,445",
    "count": 1
  }
]